Workbook
Name a: Raw_Data!$A$1:$BM$6001

Sheet Raw_Data
A1: Batch_ID | B1: Production_Date | C1: Quarter | D1: Month | E1: Month_Number | F1: Factory | G1: Production_Line | H1: Machine_ID | I1: Shift | J1: Product_Model | K1: Sales_Contract_Type | L1: Raw_Material_Supplier | M1: Material_Grade | N1: Destination_Region | O1: Shipping_Carrier | P1: Confirmed_Order_Units | Q1: Planned_Units | R1: Units_Made | S1: Defective_Units | T1: Good_Units | U1: Units_Sold | V1: Unsold_Units | W1: Defect_Rate | X1: Machine_Downtime_Min | Y1: Worker_Absence_Hours | Z1: Overtime_Hours | AA1: Selling_Price_Per_Unit | AB1: Sales_Revenue | AC1: Material_Cost_Per_Unit | AD1: Raw_Material_Cost | AE1: Labour_Cost | AF1: Electricity_Cost | AG1: Machine_Maintenance_Cost | AH1: Overtime_Cost | AI1: Defect_Rework_Cost | AJ1: Warranty_Claims_Units | AK1: Warranty_Cost | AL1: Inventory_Carrying_Cost | AM1: Shipping_Cost | AN1: Promised_Ship_Days | AO1: Actual_Ship_Days | AP1: On_Time_Shipment | AQ1: Customer_Complaints | AR1: Total_Operating_Cost | AS1: Operating_Profit | AT1: Quality_Inspection_Result | AU1: Warranty_Failure_Type | AV1: Failed_Component | AW1: Warranty_Root_Cause | AX1: Overtime_Primary_Reason | AY1: Demand_Forecast_Units | AZ1: Order_Cancellation_Units | BA1: Inventory_Age_Days | BB1: Inventory_Buildup_Reason | BC1: Dispatch_Delay_Days | BD1: Transit_Delay_Days | BE1: Shipment_Delay_Reason | BF1: Incoming_Material_Inspection_Result | BG1: Unplanned_Breakdown_Count | BH1: Machine_Breakdown_Reason | BI1: Days_Since_Preventive_Maintenance | BJ1: Preventive_Maintenance_Status | BK1: Safety_Incident_Count | BL1: Rated_Batch_Capacity_Units | BM1: Capacity_Utilization_Rate
A2: BATCH00038 | B2: 45658 | C2: Q1 2025 | D2: Jan | E2: 1 | F2: Pune Factory | G2: Line 2 | H2: PUN-L2-M2 | I2: Night | J2: Student Laptop | K2: Export Contract | L2: Zenith Parts | M2: Grade A | N2: West | O2: AirRoad Express | P2: 65 | Q2: 68 | R2: 64 | S2: 2 | T2: =R2-S2 -> 62 | U2: 62 | V2: =T2-U2 -> 0 | W2: =IFERROR(S2/R2,0) -> 0.03125 | X2: 31 | Y2: 1.1 | Z2: 0.7 | AA2: 38457.51 | AB2: =ROUND(U2*AA2,2) -> 2384365.6 | AC2: 23470.06 | AD2: =ROUND(R2*AC2,2) -> 1502083.8 | AE2: 112864.27 | AF2: 30323.99 | AG2: 10002.72 | AH2: 1015 | AI2: 6400 | AJ2: 0 | AK2: 0 | AL2: 0 | AM2: 39483 | AN2: 4 | AO2: 4 | AP2: =IF(AO2<=AN2,"Yes","No") -> Yes | AQ2: 0 | AR2: =ROUND(SUM(AD2:AI2)+SUM(AK2:AM2),2) -> 1702172.8 | AS2: =ROUND(AB2-AR2,2) -> 682192.8 | AT2: Pass | AU2: No Warranty Claim | AV2: None | AW2: Not Applicable | AX2: Recover Missed Production Target | AY2: 66 | AZ2: 0 | BA2: 0 | BB2: No Inventory Buildup | BC2: 0 | BD2: 0 | BE2: On Time | BF2: Passed | BG2: 0 | BH2: No Major Breakdown | BI2: 29 | BJ2: Up to Date | BK2: 0 | BL2: 73 | BM2: =IFERROR(R2/BL2,0) -> 0.87671233
A3: BATCH00122 | B3: 45658 | C3: Q1 2025 | D3: Jan | E3: 1 | F3: Chennai Factory | G3: Line 1 | H3: CHE-L1-M1 | I3: Morning | J3: Business Laptop | K3: Bulk Contract | L3: Nova Electronics | M3: Grade B | N3: North | O3: SwiftShip | P3: 49 | Q3: 51 | R3: 49 | S3: 2 | T3: =R3-S3 -> 47 | U3: 47 | V3: =T3-U3 -> 0 | W3: =IFERROR(S3/R3,0) -> 0.040816327 | X3: 29 | Y3: 4.6 | Z3: 1.6 | AA3: 48298.22 | AB3: =ROUND(U3*AA3,2) -> 2270016.3 | AC3: 32426.62 | AD3: =ROUND(R3*AC3,2) -> 1588904.4 | AE3: 104746.09 | AF3: 30391.96 | AG3: 9196.58 | AH3: 2320 | AI3: 9200 | AJ3: 1 | AK3: 13364.16 | AL3: 0 | AM3: 29112.74 | AN3: 4 | AO3: 3 | AP3: =IF(AO3<=AN3,"Yes","No") -> Yes | AQ3: 2 | AR3: =ROUND(SUM(AD3:AI3)+SUM(AK3:AM3),2) -> 1787235.9 | AS3: =ROUND(AB3-AR3,2) -> 482780.43 | AT3: Pass | AU3: Random Shutdown | AV3: Motherboard | AW3: Supplier Material Degradation | AX3: Recover Missed Production Target | AY3: 49 | AZ3: 0 | BA3: 0 | BB3: No Inventory Buildup | BC3: 0 | BD3: 0 | BE3: On Time | BF3: Passed with Minor Deviation | BG3: 0 | BH3: No Major Breakdown | BI3: 24 | BJ3: Up to Date | BK3: 0 | BL3: 59 | BM3: =IFERROR(R3/BL3,0) -> 0.83050847
A4: BATCH00131 | B4: 45658 | C4: Q1 2025 | D4: Jan | E4: 1 | F4: Noida Factory | G4: Line 2 | H4: NOI-L2-M1 | I4: Evening | J4: Student Laptop | K4: Regular Contract | L4: Zenith Parts | M4: Grade A | N4: South | O4: SwiftShip | P4: 57 | Q4: 58 | R4: 57 | S4: 1 | T4: =R4-S4 -> 56 | U4: 56 | V4: =T4-U4 -> 0 | W4: =IFERROR(S4/R4,0) -> 0.01754386 | X4: 8 | Y4: 2 | Z4: 0.6 | AA4: 36321.51 | AB4: =ROUND(U4*AA4,2) -> 2034004.6 | AC4: 23657.61 | AD4: =ROUND(R4*AC4,2) -> 1348483.8 | AE4: 96534.28 | AF4: 24759.98 | AG4: 7196.75 | AH4: 870 | AI4: 3200 | AJ4: 0 | AK4: 0 | AL4: 0 | AM4: 35385.5 | AN4: 4 | AO4: 3 | AP4: =IF(AO4<=AN4,"Yes","No") -> Yes | AQ4: 1 | AR4: =ROUND(SUM(AD4:AI4)+SUM(AK4:AM4),2) -> 1516430.3 | AS4: =ROUND(AB4-AR4,2) -> 517574.28 | AT4: Pass | AU4: No Warranty Claim | AV4: None | AW4: Not Applicable | AX4: Recover Missed Production Target | AY4: 58 | AZ4: 0 | BA4: 0 | BB4: No Inventory Buildup | BC4: 0 | BD4: 0 | BE4: On Time | BF4: Passed | BG4: 0 | BH4: No Major Breakdown | BI4: 18 | BJ4: Up to Date | BK4: 0 | BL4: 70 | BM4: =IFERROR(R4/BL4,0) -> 0.81428571
A5: BATCH00172 | B5: 45658 | C5: Q1 2025 | D5: Jan | E5: 1 | F5: Bengaluru Factory | G5: Line 3 | H5: BLR-L3-M4 | I5: Evening | J5: Gaming Laptop | K5: Regular Contract | L5: Zenith Parts | M5: Grade A | N5: West | O5: BlueLine Logistics | P5: 36 | Q5: 37 | R5: 36 | S5: 1 | T5: =R5-S5 -> 35 | U5: 35 | V5: =T5-U5 -> 0 | W5: =IFERROR(S5/R5,0) -> 0.027777778 | X5: 24 | Y5: 10.7 | Z5: 1.4 | AA5: 77993.24 | AB5: =ROUND(U5*AA5,2) -> 2729763.4 | AC5: 52708.96 | AD5: =ROUND(R5*AC5,2) -> 1897522.6 | AE5: 110667.05 | AF5: 34406.58 | AG5: 8628.89 | AH5: 2030 | AI5: 6800 | AJ5: 0 | AK5: 0 | AL5: 0 | AM5: 26469.08 | AN5: 4 | AO5: 6 | AP5: =IF(AO5<=AN5,"Yes","No") -> No | AQ5: 2 | AR5: =ROUND(SUM(AD5:AI5)+SUM(AK5:AM5),2) -> 2086524.2 | AS5: =ROUND(AB5-AR5,2) -> 643239.24 | AT5: Pass | AU5: No Warranty Claim | AV5: None | AW5: Not Applicable | AX5: Worker Shortage | AY5: 38 | AZ5: 0 | BA5: 0 | BB5: No Inventory Buildup | BC5: 2 | BD5: 0 | BE5: Factory Dispatch Delay | BF5: Passed | BG5: 1 | BH5: Minor Calibration Drift | BI5: 20 | BJ5: Up to Date | BK5: 0 | BL5: 48 | BM5: =IFERROR(R5/BL5,0) -> 0.75
A6: BATCH00174 | B6: 45658 | C6: Q1 2025 | D6: Jan | E6: 1 | F6: Chennai Factory | G6: Line 3 | H6: CHE-L3-M2 | I6: Morning | J6: Business Laptop | K6: Bulk Contract | L6: Zenith Parts | M6: Grade A | N6: West | O6: SwiftShip | P6: 43 | Q6: 43 | R6: 42 | S6: 1 | T6: =R6-S6 -> 41 | U6: 41 | V6: =T6-U6 -> 0 | W6: =IFERROR(S6/R6,0) -> 0.023809524 | X6: 22 | Y6: 6.1 | Z6: 0.9 | AA6: 48247.51 | AB6: =ROUND(U6*AA6,2) -> 1978147.9 | AC6: 34777.26 | AD6: =ROUND(R6*AC6,2) -> 1460644.9 | AE6: 90050.73 | AF6: 26134.54 | AG6: 9150.41 | AH6: 1305 | AI6: 4600 | AJ6: 0 | AK6: 0 | AL6: 0 | AM6: 26098.71 | AN6: 4 | AO6: 4 | AP6: =IF(AO6<=AN6,"Yes","No") -> Yes | AQ6: 1 | AR6: =ROUND(SUM(AD6:AI6)+SUM(AK6:AM6),2) -> 1617984.3 | AS6: =ROUND(AB6-AR6,2) -> 360163.6 | AT6: Pass | AU6: No Warranty Claim | AV6: None | AW6: Not Applicable | AX6: Recover Missed Production Target | AY6: 47 | AZ6: 1 | BA6: 0 | BB6: No Inventory Buildup | BC6: 0 | BD6: 0 | BE6: On Time | BF6: Passed | BG6: 1 | BH6: Minor Calibration Drift | BI6: 45 | BJ6: Up to Date | BK6: 0 | BL6: 59 | BM6: =IFERROR(R6/BL6,0) -> 0.71186441
A7: BATCH00190 | B7: 45658 | C7: Q1 2025 | D7: Jan | E7: 1 | F7: Noida Factory | G7: Line 3 | H7: NOI-L3-M4 | I7: Evening | J7: Student Laptop | K7: Bulk Contract | L7: Apex Components | M7: Grade A | N7: West | O7: AirRoad Express | P7: 52 | Q7: 55 | R7: 54 | S7: 1 | T7: =R7-S7 -> 53 | U7: 51 | V7: =T7-U7 -> 2 | W7: =IFERROR(S7/R7,0) -> 0.018518519 | X7: 17 | Y7: 4.1 | Z7: 1.9 | AA7: 33761.35 | AB7: =ROUND(U7*AA7,2) -> 1721828.9 | AC7: 24007.2 | AD7: =ROUND(R7*AC7,2) -> 1296388.8 | AE7: 91354.7 | AF7: 23837.27 | AG7: 8728 | AH7: 2755 | AI7: 3200 | AJ7: 0 | AK7: 0 | AL7: 1300.01 | AM7: 31712.69 | AN7: 4 | AO7: 3 | AP7: =IF(AO7<=AN7,"Yes","No") -> Yes | AQ7: 1 | AR7: =ROUND(SUM(AD7:AI7)+SUM(AK7:AM7),2) -> 1459276.5 | AS7: =ROUND(AB7-AR7,2) -> 262552.38 | AT7: Pass | AU7: No Warranty Claim | AV7: None | AW7: Not Applicable | AX7: Recover Missed Production Target | AY7: 54 | AZ7: 0 | BA7: 19 | BB7: Production Above Confirmed Demand | BC7: 0 | BD7: 0 | BE7: On Time | BF7: Passed | BG7: 0 | BH7: No Major Breakdown | BI7: 20 | BJ7: Up to Date | BK7: 0 | BL7: 75 | BM7: =IFERROR(R7/BL7,0) -> 0.72
A8: BATCH00210 | B8: 45658 | C8: Q1 2025 | D8: Jan | E8: 1 | F8: Pune Factory | G8: Line 2 | H8: PUN-L2-M3 | I8: Night | J8: Business Laptop | K8: Regular Contract | L8: Apex Components | M8: Grade B | N8: South | O8: BlueLine Logistics | P8: 49 | Q8: 53 | R8: 52 | S8: 2 | T8: =R8-S8 -> 50 | U8: 48 | V8: =T8-U8 -> 2 | W8: =IFERROR(S8/R8,0) -> 0.038461538 | X8: 31 | Y8: 6.2 | Z8: 2.1 | AA8: 52059.55 | AB8: =ROUND(U8*AA8,2) -> 2498858.4 | AC8: 34142.09 | AD8: =ROUND(R8*AC8,2) -> 1775388.7 | AE8: 121399.04 | AF8: 35571.13 | AG8: 10442.31 | AH8: 3045 | AI8: 9200 | AJ8: 1 | AK8: 12868.78 | AL8: 1951.61 | AM8: 32880.3 | AN8: 4 | AO8: 3 | AP8: =IF(AO8<=AN8,"Yes","No") -> Yes | AQ8: 2 | AR8: =ROUND(SUM(AD8:AI8)+SUM(AK8:AM8),2) -> 2002746.9 | AS8: =ROUND(AB8-AR8,2) -> 496111.55 | AT8: Pass | AU8: Battery Performance Failure | AV8: Battery Cell | AW8: Normal Field Failure | AX8: Recover Missed Production Target | AY8: 52 | AZ8: 0 | BA8: 14 | BB8: Production Above Confirmed Demand | BC8: 0 | BD8: 0 | BE8: On Time | BF8: Passed | BG8: 0 | BH8: No Major Breakdown | BI8: 21 | BJ8: Up to Date | BK8: 0 | BL8: 64 | BM8: =IFERROR(R8/BL8,0) -> 0.8125
A9: BATCH00236 | B9: 45658 | C9: Q1 2025 | D9: Jan | E9: 1 | F9: Bengaluru Factory | G9: Line 1 | H9: BLR-L1-M3 | I9: Night | J9: Student Laptop | K9: Regular Contract | L9: Prime Circuits | M9: Grade A | N9: North | O9: BlueLine Logistics | P9: 59 | Q9: 60 | R9: 60 | S9: 2 | T9: =R9-S9 -> 58 | U9: 57 | V9: =T9-U9 -> 1 | W9: =IFERROR(S9/R9,0) -> 0.033333333 | X9: 35 | Y9: 7.6 | Z9: 2.1 | AA9: 35645.2 | AB9: =ROUND(U9*AA9,2) -> 2031776.4 | AC9: 23915.54 | AD9: =ROUND(R9*AC9,2) -> 1434932.4 | AE9: 107555.85 | AF9: 28876.5 | AG9: 10602.84 | AH9: 3045 | AI9: 6400 | AJ9: 0 | AK9: 0 | AL9: 663.03 | AM9: 36263.44 | AN9: 4 | AO9: 4 | AP9: =IF(AO9<=AN9,"Yes","No") -> Yes | AQ9: 1 | AR9: =ROUND(SUM(AD9:AI9)+SUM(AK9:AM9),2) -> 1628339.1 | AS9: =ROUND(AB9-AR9,2) -> 403437.34 | AT9: Pass | AU9: No Warranty Claim | AV9: None | AW9: Not Applicable | AX9: Extended Quality Rework | AY9: 64 | AZ9: 2 | BA9: 13 | BB9: Order Cancellations | BC9: 0 | BD9: 0 | BE9: On Time | BF9: Passed | BG9: 1 | BH9: Short Conveyor Jam | BI9: 55 | BJ9: Due Soon | BK9: 0 | BL9: 77 | BM9: =IFERROR(R9/BL9,0) -> 0.77922078
A10: BATCH00277 | B10: 45658 | C10: Q1 2025 | D10: Jan | E10: 1 | F10: Noida Factory | G10: Line 3 | H10: NOI-L3-M4 | I10: Night | J10: Student Laptop | K10: Bulk Contract | L10: Apex Components | M10: Grade B | N10: East | O10: AirRoad Express | P10: 75 | Q10: 76 | R10: 75 | S10: 3 | T10: =R10-S10 -> 72 | U10: 72 | V10: =T10-U10 -> 0 | W10: =IFERROR(S10/R10,0) -> 0.04 | X10: 36 | Y10: 2.9 | Z10: 1.5 | AA10: 33454.28 | AB10: =ROUND(U10*AA10,2) -> 2408708.2 | AC10: 23137.65 | AD10: =ROUND(R10*AC10,2) -> 1735323.8 | AE10: 135475 | AF10: 33238.84 | AG10: 9863.48 | AH10: 2175 | AI10: 9600 | AJ10: 1 | AK10: 8872.14 | AL10: 0 | AM10: 46882.37 | AN10: 4 | AO10: 4 | AP10: =IF(AO10<=AN10,"Yes","No") -> Yes | AQ10: 2 | AR10: =ROUND(SUM(AD10:AI10)+SUM(AK10:AM10),2) -> 1981430.6 | AS10: =ROUND(AB10-AR10,2) -> 427277.58 | AT10: Pass | AU10: Battery Performance Failure | AV10: Battery Cell | AW10: Normal Field Failure | AX10: Recover Missed Production Target | AY10: 78 | AZ10: 0 | BA10: 0 | BB10: No Inventory Buildup | BC10: 0 | BD10: 0 | BE10: On Time | BF10: Passed with Minor Deviation | BG10: 1 | BH10: Minor Calibration Drift | BI10: 51 | BJ10: Due Soon | BK10: 0 | BL10: 82 | BM10: =IFERROR(R10/BL10,0) -> 0.91463415
A11: BATCH00296 | B11: 45658 | C11: Q1 2025 | D11: Jan | E11: 1 | F11: Chennai Factory | G11: Line 1 | H11: CHE-L1-M3 | I11: Night | J11: Student Laptop | K11: Bulk Contract | L11: Apex Components | M11: Grade A | N11: East | O11: BlueLine Logistics | P11: 72 | Q11: 72 | R11: 73 | S11: 2 | T11: =R11-S11 -> 71 | U11: 71 | V11: =T11-U11 -> 0 | W11: =IFERROR(S11/R11,0) -> 0.02739726 | X11: 11 | Y11: 2.1 | Z11: 1.6 | AA11: 34099.8 | AB11: =ROUND(U11*AA11,2) -> 2421085.8 | AC11: 24324.53 | AD11: =ROUND(R11*AC11,2) -> 1775690.7 | AE11: 130917.73 | AF11: 31728.64 | AG11: 7721.88 | AH11: 2320 | AI11: 6400 | AJ11: 0 | AK11: 0 | AL11: 0 | AM11: 43611.44 | AN11: 4 | AO11: 3 | AP11: =IF(AO11<=AN11,"Yes","No") -> Yes | AQ11: 1 | AR11: =ROUND(SUM(AD11:AI11)+SUM(AK11:AM11),2) -> 1998390.4 | AS11: =ROUND(AB11-AR11,2) -> 422695.42 | AT11: Pass | AU11: No Warranty Claim | AV11: None | AW11: Not Applicable | AX11: Extended Quality Rework | AY11: 76 | AZ11: 1 | BA11: 0 | BB11: No Inventory Buildup | BC11: 0 | BD11: 0 | BE11: On Time | BF11: Passed | BG11: 0 | BH11: No Major Breakdown | BI11: 8 | BJ11: Up to Date | BK11: 0 | BL11: 76 | BM11: =IFERROR(R11/BL11,0) -> 0.96052632
A12: BATCH00313 | B12: 45658 | C12: Q1 2025 | D12: Jan | E12: 1 | F12: Chennai Factory | G12: Line 3 | H12: CHE-L3-M1 | I12: Evening | J12: Student Laptop | K12: Bulk Contract | L12: Prime Circuits | M12: Grade A | N12: West | O12: BlueLine Logistics | P12: 54 | Q12: 56 | R12: 53 | S12: 1 | T12: =R12-S12 -> 52 | U12: 52 | V12: =T12-U12 -> 0 | W12: =IFERROR(S12/R12,0) -> 0.018867925 | X12: 26 | Y12: 3.6 | Z12: 1.2 | AA12: 33422.48 | AB12: =ROUND(U12*AA12,2) -> 1737969 | AC12: 23682.35 | AD12: =ROUND(R12*AC12,2) -> 1255164.6 | AE12: 89839.01 | AF12: 23336.53 | AG12: 9190.48 | AH12: 1740 | AI12: 3200 | AJ12: 0 | AK12: 0 | AL12: 0 | AM12: 32139.62 | AN12: 4 | AO12: 4 | AP12: =IF(AO12<=AN12,"Yes","No") -> Yes | AQ12: 0 | AR12: =ROUND(SUM(AD12:AI12)+SUM(AK12:AM12),2) -> 1414610.2 | AS12: =ROUND(AB12-AR12,2) -> 323358.77 | AT12: Pass | AU12: No Warranty Claim | AV12: None | AW12: Not Applicable | AX12: Recover Missed Production Target | AY12: 58 | AZ12: 2 | BA12: 0 | BB12: No Inventory Buildup | BC12: 0 | BD12: 0 | BE12: On Time | BF12: Passed | BG12: 0 | BH12: No Major Breakdown | BI12: 22 | BJ12: Up to Date | BK12: 0 | BL12: 76 | BM12: =IFERROR(R12/BL12,0) -> 0.69736842
A13: BATCH00333 | B13: 45658 | C13: Q1 2025 | D13: Jan | E13: 1 | F13: Chennai Factory | G13: Line 3 | H13: CHE-L3-M4 | I13: Night | J13: Gaming Laptop | K13: Regular Contract | L13: Apex Components | M13: Grade A | N13: South | O13: BlueLine Logistics | P13: 32 | Q13: 34 | R13: 33 | S13: 1 | T13: =R13-S13 -> 32 | U13: 32 | V13: =T13-U13 -> 0 | W13: =IFERROR(S13/R13,0) -> 0.03030303 | X13: 34 | Y13: 2.5 | Z13: 1.2 | AA13: 78237.93 | AB13: =ROUND(U13*AA13,2) -> 2503613.8 | AC13: 54104.31 | AD13: =ROUND(R13*AC13,2) -> 1785442.2 | AE13: 106653.06 | AF13: 28352.95 | AG13: 9764.94 | AH13: 1740 | AI13: 6800 | AJ13: 0 | AK13: 0 | AL13: 0 | AM13: 23820.87 | AN13: 4 | AO13: 5 | AP13: =IF(AO13<=AN13,"Yes","No") -> No | AQ13: 1 | AR13: =ROUND(SUM(AD13:AI13)+SUM(AK13:AM13),2) -> 1962574.1 | AS13: =ROUND(AB13-AR13,2) -> 541039.71 | AT13: Pass | AU13: No Warranty Claim | AV13: None | AW13: Not Applicable | AX13: Recover Missed Production Target | AY13: 34 | AZ13: 0 | BA13: 0 | BB13: No Inventory Buildup | BC13: 0 | BD13: 1 | BE13: Carrier Transit Delay | BF13: Passed | BG13: 1 | BH13: Minor Calibration Drift | BI13: 38 | BJ13: Up to Date | BK13: 0 | BL13: 47 | BM13: =IFERROR(R13/BL13,0) -> 0.70212766
... A6001: BATCH05915 | B6001: 46022 | C6001: Q4 2025 | D6001: Dec | E6001: 12 | F6001: Noida Factory | G6001: Line 1 | H6001: NOI-L1-M4 | I6001: Evening | J6001: Student Laptop | K6001: Regular Contract | L6001: Zenith Parts | M6001: Grade A | N6001: South | O6001: AirRoad Express | P6001: 60 | Q6001: 63 | R6001: 65 | S6001: 1 | T6001: =R6001-S6001 -> 64 | U6001: 59 | V6001: =T6001-U6001 -> 5 | W6001: =IFERROR(S6001/R6001,0) -> 0.015384615 | X6001: 24 | Y6001: 1.5 | Z6001: 1 | AA6001: 35731.27 | AB6001: =ROUND(U6001*AA6001,2) -> 2108144.9 | AC6001: 23717.87 | AD6001: =ROUND(R6001*AC6001,2) -> 1541661.6 | AE6001: 111779.11 | AF6001: 28452.57 | AG6001: 8559.51 | AH6001: 1450 | AI6001: 3200 | AJ6001: 0 | AK6001: 0 | AL6001: 3291.63 | AM6001: 36547.2 | AN6001: 4 | AO6001: 3 | AP6001: =IF(AO6001<=AN6001,"Yes","No") -> Yes | AQ6001: 1 | AR6001: =ROUND(SUM(AD6001:AI6001)+SUM(AK6001:AM6001),2) -> 1734941.6 | AS6001: =ROUND(AB6001-AR6001,2) -> 373203.36 | AT6001: Pass | AU6001: No Warranty Claim | AV6001: None | AW6001: Not Applicable | AX6001: Extended Quality Rework | AY6001: 63 | AZ6001: 0 | BA6001: 28 | BB6001: Production Above Confirmed Demand | BC6001: 0 | BD6001: 0 | BE6001: On Time | BF6001: Passed | BG6001: 0 | BH6001: No Major Breakdown | BI6001: 31 | BJ6001: Up to Date | BK6001: 0 | BL6001: 72 | BM6001: =IFERROR(R6001/BL6001,0) -> 0.90277778

Sheet Q8_Capacity_Expansion
A1: Which factory is operationally safest for the next capacity expansion?
E4: AVG
A5: Factory | B5: Capacity_Utilization_Rate | C5: OP_Profit | D5: Total Loss | E5: Defect Rate | F5: Machine Downtime (Min) | G5: On-Time Shipment -YES | H5: On-Time Shipment % | I5: Total Safety Incidents
A6: Chennai Factory | B6: =SUMIFS(Raw_Data!$R$2:$R$6001,Raw_Data!$F$2:$F$6001,A6)/SUMIFS(Raw_Data!$BL$2:$BL$6001,Raw_Data!$F$2:$F$6001,A6) -> 0.82142459 | C6: 6.9943166e+08 | D6: -725383.96 | E6: =SUMIFS(Raw_Data!$S$2:$S$6001,Raw_Data!$F$2:$F$6001,$A6)/SUMIFS(Raw_Data!$R$2:$R$6001,Raw_Data!$F$2:$F$6001,$A6) -> 0.024955305 | F6: =AVERAGEIFS(Raw_Data!$X$2:$X$6001,Raw_Data!$F$2:$F$6001,$A6) -> 26.725753 | G6: =COUNTIFS(Raw_Data!$F$2:$F$6001,$A6,Raw_Data!$AP$2:$AP$6001,"Yes") -> 1037 | H6: =COUNTIFS(Raw_Data!$F$2:$F$6001,$A6,Raw_Data!$AP$2:$AP$6001,"Yes")/COUNTIF(Raw_Data!$F$2:$F$6001,$A6) -> 0.69364548 | I6: =SUMIFS(Raw_Data!$BK$2:$BK$6001,Raw_Data!$F$2:$F$6001,$A6) -> 13
A7: Noida Factory | B7: =SUMIFS(Raw_Data!$R$2:$R$6001,Raw_Data!$F$2:$F$6001,A7)/SUMIFS(Raw_Data!$BL$2:$BL$6001,Raw_Data!$F$2:$F$6001,A7) -> 0.84451768 | C7: 6.5275647e+08 | D7: -1205513.9 | E7: =SUMIFS(Raw_Data!$S$2:$S$6001,Raw_Data!$F$2:$F$6001,$A7)/SUMIFS(Raw_Data!$R$2:$R$6001,Raw_Data!$F$2:$F$6001,$A7) -> 0.021319617 | F7: =AVERAGEIFS(Raw_Data!$X$2:$X$6001,Raw_Data!$F$2:$F$6001,$A7) -> 23.247354 | G7: =COUNTIFS(Raw_Data!$F$2:$F$6001,$A7,Raw_Data!$AP$2:$AP$6001,"Yes") -> 1051 | H7: =COUNTIFS(Raw_Data!$F$2:$F$6001,$A7,Raw_Data!$AP$2:$AP$6001,"Yes")/COUNTIF(Raw_Data!$F$2:$F$6001,$A7) -> 0.69510582 | I7: =SUMIFS(Raw_Data!$BK$2:$BK$6001,Raw_Data!$F$2:$F$6001,$A7) -> 7
A8: Pune Factory | B8: =SUMIFS(Raw_Data!$R$2:$R$6001,Raw_Data!$F$2:$F$6001,A8)/SUMIFS(Raw_Data!$BL$2:$BL$6001,Raw_Data!$F$2:$F$6001,A8) -> 0.81734099 | C8: 6.3362355e+08 | D8: -35089504 | E8: =SUMIFS(Raw_Data!$S$2:$S$6001,Raw_Data!$F$2:$F$6001,$A8)/SUMIFS(Raw_Data!$R$2:$R$6001,Raw_Data!$F$2:$F$6001,$A8) -> 0.040054835 | F8: =AVERAGEIFS(Raw_Data!$X$2:$X$6001,Raw_Data!$F$2:$F$6001,$A8) -> 33.167001 | G8: =COUNTIFS(Raw_Data!$F$2:$F$6001,$A8,Raw_Data!$AP$2:$AP$6001,"Yes") -> 1035 | H8: =COUNTIFS(Raw_Data!$F$2:$F$6001,$A8,Raw_Data!$AP$2:$AP$6001,"Yes")/COUNTIF(Raw_Data!$F$2:$F$6001,$A8) -> 0.69138277 | I8: =SUMIFS(Raw_Data!$BK$2:$BK$6001,Raw_Data!$F$2:$F$6001,$A8) -> 18
A9: Bengaluru Factory | B9: =SUMIFS(Raw_Data!$R$2:$R$6001,Raw_Data!$F$2:$F$6001,A9)/SUMIFS(Raw_Data!$BL$2:$BL$6001,Raw_Data!$F$2:$F$6001,A9) -> 0.81150688 | C9: 6.1298649e+08 | D9: -49154431 | E9: =SUMIFS(Raw_Data!$S$2:$S$6001,Raw_Data!$F$2:$F$6001,$A9)/SUMIFS(Raw_Data!$R$2:$R$6001,Raw_Data!$F$2:$F$6001,$A9) -> 0.040935746 | F9: =AVERAGEIFS(Raw_Data!$X$2:$X$6001,Raw_Data!$F$2:$F$6001,$A9) -> 30.720588 | G9: =COUNTIFS(Raw_Data!$F$2:$F$6001,$A9,Raw_Data!$AP$2:$AP$6001,"Yes") -> 1046 | H9: =COUNTIFS(Raw_Data!$F$2:$F$6001,$A9,Raw_Data!$AP$2:$AP$6001,"Yes")/COUNTIF(Raw_Data!$F$2:$F$6001,$A9) -> 0.69919786 | I9: =SUMIFS(Raw_Data!$BK$2:$BK$6001,Raw_Data!$F$2:$F$6001,$A9) -> 21

Sheet Q7_Night_Shift
A1: Is the Night shift poor everywhere, or only in specific factory/line/machine combinations?
A8: Shift | B8: Weighted Defect Rate | C8: Avg Machine Downtime (Min) | D8: Avg Worker Absence (Hours) | E8: Total Operating Profit
A9: Night | B9: =SUMIFS(Raw_Data!$S$2:$S$6001,Raw_Data!$I$2:$I$6001,$A9)/SUMIFS(Raw_Data!$R$2:$R$6001,Raw_Data!$I$2:$I$6001,$A9) -> 0.034929983 | C9: =AVERAGEIFS(Raw_Data!$X$2:$X$6001,Raw_Data!$I$2:$I$6001,$A9) -> 35.176 | D9: =AVERAGEIFS(Raw_Data!$Y$2:$Y$6001,Raw_Data!$I$2:$I$6001,$A9) -> 4.1291 | E9: =SUMIFS(Raw_Data!$AS$2:$AS$6001,Raw_Data!$I$2:$I$6001,$A9) -> 8.4107917e+08
A10: Morning | B10: =SUMIFS(Raw_Data!$S$2:$S$6001,Raw_Data!$I$2:$I$6001,$A10)/SUMIFS(Raw_Data!$R$2:$R$6001,Raw_Data!$I$2:$I$6001,$A10) -> 0.029602528 | C10: =AVERAGEIFS(Raw_Data!$X$2:$X$6001,Raw_Data!$I$2:$I$6001,$A10) -> 23.302 | D10: =AVERAGEIFS(Raw_Data!$Y$2:$Y$6001,Raw_Data!$I$2:$I$6001,$A10) -> 4.25235 | E10: =SUMIFS(Raw_Data!$AS$2:$AS$6001,Raw_Data!$I$2:$I$6001,$A10) -> 8.8262538e+08
A11: Evening | B11: =SUMIFS(Raw_Data!$S$2:$S$6001,Raw_Data!$I$2:$I$6001,$A11)/SUMIFS(Raw_Data!$R$2:$R$6001,Raw_Data!$I$2:$I$6001,$A11) -> 0.030381562 | C11: =AVERAGEIFS(Raw_Data!$X$2:$X$6001,Raw_Data!$I$2:$I$6001,$A11) -> 26.879 | D11: =AVERAGEIFS(Raw_Data!$Y$2:$Y$6001,Raw_Data!$I$2:$I$6001,$A11) -> 4.62055 | E11: =SUMIFS(Raw_Data!$AS$2:$AS$6001,Raw_Data!$I$2:$I$6001,$A11) -> 8.7509362e+08
A13: Night
A14: Factory | B14: Weighted Defect Rate | C14: Machine_Downtime_Min | D14: Total Operating Profit
A15: Pune Factory | B15: =SUMIFS(Raw_Data!$S$2:$S$6001,Raw_Data!$I$2:$I$6001,"Night",Raw_Data!$F$2:$F$6001,$A15)/SUMIFS(Raw_Data!$R$2:$R$6001,Raw_Data!$I$2:$I$6001,"Night",Raw_Data!$F$2:$F$6001,$A15) -> 0.044439345 | C15: =AVERAGEIFS(Raw_Data!$X$2:$X$6001,Raw_Data!$I$2:$I$6001,"Night",Raw_Data!$F$2:$F$6001,$A15) -> 46.208925 | D15: =SUMIFS(Raw_Data!$AS$2:$AS$6001,Raw_Data!$I$2:$I$6001,"Night",Raw_Data!$F$2:$F$6001,$A15) -> 1.9836009e+08
A16: Chennai Factory | B16: =SUMIFS(Raw_Data!$S$2:$S$6001,Raw_Data!$I$2:$I$6001,"Night",Raw_Data!$F$2:$F$6001,$A16)/SUMIFS(Raw_Data!$R$2:$R$6001,Raw_Data!$I$2:$I$6001,"Night",Raw_Data!$F$2:$F$6001,$A16) -> 0.027542529 | C16: =AVERAGEIFS(Raw_Data!$X$2:$X$6001,Raw_Data!$I$2:$I$6001,"Night",Raw_Data!$F$2:$F$6001,$A16) -> 30.215842 | D16: =SUMIFS(Raw_Data!$AS$2:$AS$6001,Raw_Data!$I$2:$I$6001,"Night",Raw_Data!$F$2:$F$6001,$A16) -> 2.3068417e+08
A17: Noida Factory | B17: =SUMIFS(Raw_Data!$S$2:$S$6001,Raw_Data!$I$2:$I$6001,"Night",Raw_Data!$F$2:$F$6001,$A17)/SUMIFS(Raw_Data!$R$2:$R$6001,Raw_Data!$I$2:$I$6001,"Night",Raw_Data!$F$2:$F$6001,$A17) -> 0.024209818 | C17: =AVERAGEIFS(Raw_Data!$X$2:$X$6001,Raw_Data!$I$2:$I$6001,"Night",Raw_Data!$F$2:$F$6001,$A17) -> 27.333333 | D17: =SUMIFS(Raw_Data!$AS$2:$AS$6001,Raw_Data!$I$2:$I$6001,"Night",Raw_Data!$F$2:$F$6001,$A17) -> 2.1224191e+08
A18: Bengaluru Factory | B18: =SUMIFS(Raw_Data!$S$2:$S$6001,Raw_Data!$I$2:$I$6001,"Night",Raw_Data!$F$2:$F$6001,$A18)/SUMIFS(Raw_Data!$R$2:$R$6001,Raw_Data!$I$2:$I$6001,"Night",Raw_Data!$F$2:$F$6001,$A18) -> 0.044449425 | C18: =AVERAGEIFS(Raw_Data!$X$2:$X$6001,Raw_Data!$I$2:$I$6001,"Night",Raw_Data!$F$2:$F$6001,$A18) -> 37.220884 | D18: =SUMIFS(Raw_Data!$AS$2:$AS$6001,Raw_Data!$I$2:$I$6001,"Night",Raw_Data!$F$2:$F$6001,$A18) -> 1.99793e+08
A21: Pune Factory | B21: Weighted Defect Rate | C21: Avg Machine Downtime (Min) | D21: Total Operating Profit
A22: {=_xlfn._xlws.SORT(_xlfn.UNIQUE(_xlfn._xlws.FILTER(Raw_Data!$H$2:$H$6001,(Raw_Data!$F$2:$F$6001="Pune Factory")*(Raw_Data!$I$2:$I$6001="Night"))))} -> PUN-L1-M1 | B22: =SUMIFS(Raw_Data!$S$2:$S$6001,Raw_Data!$F$2:$F$6001,"Pune Factory",Raw_Data!$I$2:$I$6001,"Night",Raw_Data!$H$2:$H$6001,$A22)/SUMIFS(Raw_Data!$R$2:$R$6001,Raw_Data!$F$2:$F$6001,"Pune Factory",Raw_Data!$I$2:$I$6001,"Night",Raw_Data!$H$2:$H$6001,$A22) -> 0.036211699 | C22: =AVERAGEIFS(Raw_Data!$X$2:$X$6001,Raw_Data!$F$2:$F$6001,"Pune Factory",Raw_Data!$I$2:$I$6001,"Night",Raw_Data!$H$2:$H$6001,$A22) -> 34.725 | D22: =SUMIFS(Raw_Data!$AS$2:$AS$6001,Raw_Data!$F$2:$F$6001,"Pune Factory",Raw_Data!$I$2:$I$6001,"Night",Raw_Data!$H$2:$H$6001,$A22) -> 16195888
A23: PUN-L1-M2 | B23: =SUMIFS(Raw_Data!$S$2:$S$6001,Raw_Data!$F$2:$F$6001,"Pune Factory",Raw_Data!$I$2:$I$6001,"Night",Raw_Data!$H$2:$H$6001,$A23)/SUMIFS(Raw_Data!$R$2:$R$6001,Raw_Data!$F$2:$F$6001,"Pune Factory",Raw_Data!$I$2:$I$6001,"Night",Raw_Data!$H$2:$H$6001,$A23) -> 0.045812808 | C23: =AVERAGEIFS(Raw_Data!$X$2:$X$6001,Raw_Data!$F$2:$F$6001,"Pune Factory",Raw_Data!$I$2:$I$6001,"Night",Raw_Data!$H$2:$H$6001,$A23) -> 32.325 | D23: =SUMIFS(Raw_Data!$AS$2:$AS$6001,Raw_Data!$F$2:$F$6001,"Pune Factory",Raw_Data!$I$2:$I$6001,"Night",Raw_Data!$H$2:$H$6001,$A23) -> 17992569
A24: PUN-L1-M3 | B24: =SUMIFS(Raw_Data!$S$2:$S$6001,Raw_Data!$F$2:$F$6001,"Pune Factory",Raw_Data!$I$2:$I$6001,"Night",Raw_Data!$H$2:$H$6001,$A24)/SUMIFS(Raw_Data!$R$2:$R$6001,Raw_Data!$F$2:$F$6001,"Pune Factory",Raw_Data!$I$2:$I$6001,"Night",Raw_Data!$H$2:$H$6001,$A24) -> 0.037762238 | C24: =AVERAGEIFS(Raw_Data!$X$2:$X$6001,Raw_Data!$F$2:$F$6001,"Pune Factory",Raw_Data!$I$2:$I$6001,"Night",Raw_Data!$H$2:$H$6001,$A24) -> 30.341463 | D24: =SUMIFS(Raw_Data!$AS$2:$AS$6001,Raw_Data!$F$2:$F$6001,"Pune Factory",Raw_Data!$I$2:$I$6001,"Night",Raw_Data!$H$2:$H$6001,$A24) -> 19070967
A25: PUN-L1-M4 | B25: =SUMIFS(Raw_Data!$S$2:$S$6001,Raw_Data!$F$2:$F$6001,"Pune Factory",Raw_Data!$I$2:$I$6001,"Night",Raw_Data!$H$2:$H$6001,$A25)/SUMIFS(Raw_Data!$R$2:$R$6001,Raw_Data!$F$2:$F$6001,"Pune Factory",Raw_Data!$I$2:$I$6001,"Night",Raw_Data!$H$2:$H$6001,$A25) -> 0.048309179 | C25: =AVERAGEIFS(Raw_Data!$X$2:$X$6001,Raw_Data!$F$2:$F$6001,"Pune Factory",Raw_Data!$I$2:$I$6001,"Night",Raw_Data!$H$2:$H$6001,$A25) -> 35.341463 | D25: =SUMIFS(Raw_Data!$AS$2:$AS$6001,Raw_Data!$F$2:$F$6001,"Pune Factory",Raw_Data!$I$2:$I$6001,"Night",Raw_Data!$H$2:$H$6001,$A25) -> 14597605
A26: PUN-L2-M1 | B26: =SUMIFS(Raw_Data!$S$2:$S$6001,Raw_Data!$F$2:$F$6001,"Pune Factory",Raw_Data!$I$2:$I$6001,"Night",Raw_Data!$H$2:$H$6001,$A26)/SUMIFS(Raw_Data!$R$2:$R$6001,Raw_Data!$F$2:$F$6001,"Pune Factory",Raw_Data!$I$2:$I$6001,"Night",Raw_Data!$H$2:$H$6001,$A26) -> 0.038961039 | C26: =AVERAGEIFS(Raw_Data!$X$2:$X$6001,Raw_Data!$F$2:$F$6001,"Pune Factory",Raw_Data!$I$2:$I$6001,"Night",Raw_Data!$H$2:$H$6001,$A26) -> 32.55 | D26: =SUMIFS(Raw_Data!$AS$2:$AS$6001,Raw_Data!$F$2:$F$6001,"Pune Factory",Raw_Data!$I$2:$I$6001,"Night",Raw_Data!$H$2:$H$6001,$A26) -> 17851954
A27: PUN-L2-M2 | B27: =SUMIFS(Raw_Data!$S$2:$S$6001,Raw_Data!$F$2:$F$6001,"Pune Factory",Raw_Data!$I$2:$I$6001,"Night",Raw_Data!$H$2:$H$6001,$A27)/SUMIFS(Raw_Data!$R$2:$R$6001,Raw_Data!$F$2:$F$6001,"Pune Factory",Raw_Data!$I$2:$I$6001,"Night",Raw_Data!$H$2:$H$6001,$A27) -> 0.041556145 | C27: =AVERAGEIFS(Raw_Data!$X$2:$X$6001,Raw_Data!$F$2:$F$6001,"Pune Factory",Raw_Data!$I$2:$I$6001,"Night",Raw_Data!$H$2:$H$6001,$A27) -> 31.170732 | D27: =SUMIFS(Raw_Data!$AS$2:$AS$6001,Raw_Data!$F$2:$F$6001,"Pune Factory",Raw_Data!$I$2:$I$6001,"Night",Raw_Data!$H$2:$H$6001,$A27) -> 17836405
A28: PUN-L2-M3 | B28: =SUMIFS(Raw_Data!$S$2:$S$6001,Raw_Data!$F$2:$F$6001,"Pune Factory",Raw_Data!$I$2:$I$6001,"Night",Raw_Data!$H$2:$H$6001,$A28)/SUMIFS(Raw_Data!$R$2:$R$6001,Raw_Data!$F$2:$F$6001,"Pune Factory",Raw_Data!$I$2:$I$6001,"Night",Raw_Data!$H$2:$H$6001,$A28) -> 0.043515726 | C28: =AVERAGEIFS(Raw_Data!$X$2:$X$6001,Raw_Data!$F$2:$F$6001,"Pune Factory",Raw_Data!$I$2:$I$6001,"Night",Raw_Data!$H$2:$H$6001,$A28) -> 34.166667 | D28: =SUMIFS(Raw_Data!$AS$2:$AS$6001,Raw_Data!$F$2:$F$6001,"Pune Factory",Raw_Data!$I$2:$I$6001,"Night",Raw_Data!$H$2:$H$6001,$A28) -> 18477822
A29: PUN-L2-M4 | B29: =SUMIFS(Raw_Data!$S$2:$S$6001,Raw_Data!$F$2:$F$6001,"Pune Factory",Raw_Data!$I$2:$I$6001,"Night",Raw_Data!$H$2:$H$6001,$A29)/SUMIFS(Raw_Data!$R$2:$R$6001,Raw_Data!$F$2:$F$6001,"Pune Factory",Raw_Data!$I$2:$I$6001,"Night",Raw_Data!$H$2:$H$6001,$A29) -> 0.042259991 | C29: =AVERAGEIFS(Raw_Data!$X$2:$X$6001,Raw_Data!$F$2:$F$6001,"Pune Factory",Raw_Data!$I$2:$I$6001,"Night",Raw_Data!$H$2:$H$6001,$A29) -> 31.02381 | D29: =SUMIFS(Raw_Data!$AS$2:$AS$6001,Raw_Data!$F$2:$F$6001,"Pune Factory",Raw_Data!$I$2:$I$6001,"Night",Raw_Data!$H$2:$H$6001,$A29) -> 17145742
A30: PUN-L3-M1 | B30: =SUMIFS(Raw_Data!$S$2:$S$6001,Raw_Data!$F$2:$F$6001,"Pune Factory",Raw_Data!$I$2:$I$6001,"Night",Raw_Data!$H$2:$H$6001,$A30)/SUMIFS(Raw_Data!$R$2:$R$6001,Raw_Data!$F$2:$F$6001,"Pune Factory",Raw_Data!$I$2:$I$6001,"Night",Raw_Data!$H$2:$H$6001,$A30) -> 0.047705588 | C30: =AVERAGEIFS(Raw_Data!$X$2:$X$6001,Raw_Data!$F$2:$F$6001,"Pune Factory",Raw_Data!$I$2:$I$6001,"Night",Raw_Data!$H$2:$H$6001,$A30) -> 31.333333 | D30: =SUMIFS(Raw_Data!$AS$2:$AS$6001,Raw_Data!$F$2:$F$6001,"Pune Factory",Raw_Data!$I$2:$I$6001,"Night",Raw_Data!$H$2:$H$6001,$A30) -> 17985495
A31: PUN-L3-M2 | B31: =SUMIFS(Raw_Data!$S$2:$S$6001,Raw_Data!$F$2:$F$6001,"Pune Factory",Raw_Data!$I$2:$I$6001,"Night",Raw_Data!$H$2:$H$6001,$A31)/SUMIFS(Raw_Data!$R$2:$R$6001,Raw_Data!$F$2:$F$6001,"Pune Factory",Raw_Data!$I$2:$I$6001,"Night",Raw_Data!$H$2:$H$6001,$A31) -> 0.043699187 | C31: =AVERAGEIFS(Raw_Data!$X$2:$X$6001,Raw_Data!$F$2:$F$6001,"Pune Factory",Raw_Data!$I$2:$I$6001,"Night",Raw_Data!$H$2:$H$6001,$A31) -> 32.615385 | D31: =SUMIFS(Raw_Data!$AS$2:$AS$6001,Raw_Data!$F$2:$F$6001,"Pune Factory",Raw_Data!$I$2:$I$6001,"Night",Raw_Data!$H$2:$H$6001,$A31) -> 16496468
A32: PUN-L3-M3 | B32: =SUMIFS(Raw_Data!$S$2:$S$6001,Raw_Data!$F$2:$F$6001,"Pune Factory",Raw_Data!$I$2:$I$6001,"Night",Raw_Data!$H$2:$H$6001,$A32)/SUMIFS(Raw_Data!$R$2:$R$6001,Raw_Data!$F$2:$F$6001,"Pune Factory",Raw_Data!$I$2:$I$6001,"Night",Raw_Data!$H$2:$H$6001,$A32) -> 0.053618134 | C32: =AVERAGEIFS(Raw_Data!$X$2:$X$6001,Raw_Data!$F$2:$F$6001,"Pune Factory",Raw_Data!$I$2:$I$6001,"Night",Raw_Data!$H$2:$H$6001,$A32) -> 110.95455 | D32: =SUMIFS(Raw_Data!$AS$2:$AS$6001,Raw_Data!$F$2:$F$6001,"Pune Factory",Raw_Data!$I$2:$I$6001,"Night",Raw_Data!$H$2:$H$6001,$A32) -> 10413856
A33: PUN-L3-M4 | B33: =SUMIFS(Raw_Data!$S$2:$S$6001,Raw_Data!$F$2:$F$6001,"Pune Factory",Raw_Data!$I$2:$I$6001,"Night",Raw_Data!$H$2:$H$6001,$A33)/SUMIFS(Raw_Data!$R$2:$R$6001,Raw_Data!$F$2:$F$6001,"Pune Factory",Raw_Data!$I$2:$I$6001,"Night",Raw_Data!$H$2:$H$6001,$A33) -> 0.052678571 | C33: =AVERAGEIFS(Raw_Data!$X$2:$X$6001,Raw_Data!$F$2:$F$6001,"Pune Factory",Raw_Data!$I$2:$I$6001,"Night",Raw_Data!$H$2:$H$6001,$A33) -> 112.63415 | D33: =SUMIFS(Raw_Data!$AS$2:$AS$6001,Raw_Data!$F$2:$F$6001,"Pune Factory",Raw_Data!$I$2:$I$6001,"Night",Raw_Data!$H$2:$H$6001,$A33) -> 14295315

Sheet Q6_Maintenance_Priority
A1: Which machines should receive preventive maintenance first?
I3: Top Preventive Maintenance Priorities
B4: Preventive_Maintenance_Status | I4: Machine | J4: Overdue | K4: Due Soon | L4: Total Machine Downtime (Min)
A5: Machines | B5: Up to Date | C5: Due Soon | D5: Overdue | E5: Total Machine Downtime (Min) | I5: PUN-L3-M3 | J5: 97 | K5: 6 | L5: 7139
A6: PUN-L3-M3 | B6: =COUNTIFS(Raw_Data!$H$2:$H$6001,A6,Raw_Data!$BJ$2:$BJ$6001,"Up to Date") -> 25 | C6: =COUNTIFS(Raw_Data!$H$2:$H$6001,A6,Raw_Data!$BJ$2:$BJ$6001,"Due Soon") -> 6 | D6: =COUNTIFS(Raw_Data!$H$2:$H$6001,A6,Raw_Data!$BJ$2:$BJ$6001,"Overdue") -> 97 | E6: =SUMIFS(Raw_Data!$X$2:$X$6001,Raw_Data!$H$2:$H$6001,A6) -> 7139 | I6: PUN-L3-M4 | J6: 99 | K6: 12 | L6: 6990
A7: PUN-L3-M4 | B7: =COUNTIFS(Raw_Data!$H$2:$H$6001,A7,Raw_Data!$BJ$2:$BJ$6001,"Up to Date") -> 20 | C7: =COUNTIFS(Raw_Data!$H$2:$H$6001,A7,Raw_Data!$BJ$2:$BJ$6001,"Due Soon") -> 12 | D7: =COUNTIFS(Raw_Data!$H$2:$H$6001,A7,Raw_Data!$BJ$2:$BJ$6001,"Overdue") -> 99 | E7: =SUMIFS(Raw_Data!$X$2:$X$6001,Raw_Data!$H$2:$H$6001,A7) -> 6990 | I7: BLR-L2-M2 | J7: 96 | K7: 7 | L7: 5724
A8: BLR-L2-M2 | B8: =COUNTIFS(Raw_Data!$H$2:$H$6001,A8,Raw_Data!$BJ$2:$BJ$6001,"Up to Date") -> 24 | C8: =COUNTIFS(Raw_Data!$H$2:$H$6001,A8,Raw_Data!$BJ$2:$BJ$6001,"Due Soon") -> 7 | D8: =COUNTIFS(Raw_Data!$H$2:$H$6001,A8,Raw_Data!$BJ$2:$BJ$6001,"Overdue") -> 96 | E8: =SUMIFS(Raw_Data!$X$2:$X$6001,Raw_Data!$H$2:$H$6001,A8) -> 5724
A9: BLR-L2-M1 | B9: =COUNTIFS(Raw_Data!$H$2:$H$6001,A9,Raw_Data!$BJ$2:$BJ$6001,"Up to Date") -> 99 | C9: =COUNTIFS(Raw_Data!$H$2:$H$6001,A9,Raw_Data!$BJ$2:$BJ$6001,"Due Soon") -> 25 | D9: =COUNTIFS(Raw_Data!$H$2:$H$6001,A9,Raw_Data!$BJ$2:$BJ$6001,"Overdue") -> 6 | E9: =SUMIFS(Raw_Data!$X$2:$X$6001,Raw_Data!$H$2:$H$6001,A9) -> 3833
A10: BLR-L1-M3 | B10: =COUNTIFS(Raw_Data!$H$2:$H$6001,A10,Raw_Data!$BJ$2:$BJ$6001,"Up to Date") -> 96 | C10: =COUNTIFS(Raw_Data!$H$2:$H$6001,A10,Raw_Data!$BJ$2:$BJ$6001,"Due Soon") -> 27 | D10: =COUNTIFS(Raw_Data!$H$2:$H$6001,A10,Raw_Data!$BJ$2:$BJ$6001,"Overdue") -> 6 | E10: =SUMIFS(Raw_Data!$X$2:$X$6001,Raw_Data!$H$2:$H$6001,A10) -> 3810
A11: BLR-L1-M2 | B11: =COUNTIFS(Raw_Data!$H$2:$H$6001,A11,Raw_Data!$BJ$2:$BJ$6001,"Up to Date") -> 88 | C11: =COUNTIFS(Raw_Data!$H$2:$H$6001,A11,Raw_Data!$BJ$2:$BJ$6001,"Due Soon") -> 35 | D11: =COUNTIFS(Raw_Data!$H$2:$H$6001,A11,Raw_Data!$BJ$2:$BJ$6001,"Overdue") -> 7 | E11: =SUMIFS(Raw_Data!$X$2:$X$6001,Raw_Data!$H$2:$H$6001,A11) -> 3808
A12: BLR-L3-M2 | B12: =COUNTIFS(Raw_Data!$H$2:$H$6001,A12,Raw_Data!$BJ$2:$BJ$6001,"Up to Date") -> 95 | C12: =COUNTIFS(Raw_Data!$H$2:$H$6001,A12,Raw_Data!$BJ$2:$BJ$6001,"Due Soon") -> 21 | D12: =COUNTIFS(Raw_Data!$H$2:$H$6001,A12,Raw_Data!$BJ$2:$BJ$6001,"Overdue") -> 8 | E12: =SUMIFS(Raw_Data!$X$2:$X$6001,Raw_Data!$H$2:$H$6001,A12) -> 3793
A13: BLR-L2-M4 | B13: =COUNTIFS(Raw_Data!$H$2:$H$6001,A13,Raw_Data!$BJ$2:$BJ$6001,"Up to Date") -> 94 | C13: =COUNTIFS(Raw_Data!$H$2:$H$6001,A13,Raw_Data!$BJ$2:$BJ$6001,"Due Soon") -> 24 | D13: =COUNTIFS(Raw_Data!$H$2:$H$6001,A13,Raw_Data!$BJ$2:$BJ$6001,"Overdue") -> 5 | E13: =SUMIFS(Raw_Data!$X$2:$X$6001,Raw_Data!$H$2:$H$6001,A13) -> 3784
A14: PUN-L1-M2 | B14: =COUNTIFS(Raw_Data!$H$2:$H$6001,A14,Raw_Data!$BJ$2:$BJ$6001,"Up to Date") -> 94 | C14: =COUNTIFS(Raw_Data!$H$2:$H$6001,A14,Raw_Data!$BJ$2:$BJ$6001,"Due Soon") -> 29 | D14: =COUNTIFS(Raw_Data!$H$2:$H$6001,A14,Raw_Data!$BJ$2:$BJ$6001,"Overdue") -> 2 | E14: =SUMIFS(Raw_Data!$X$2:$X$6001,Raw_Data!$H$2:$H$6001,A14) -> 3704
A15: PUN-L1-M3 | B15: =COUNTIFS(Raw_Data!$H$2:$H$6001,A15,Raw_Data!$BJ$2:$BJ$6001,"Up to Date") -> 96 | C15: =COUNTIFS(Raw_Data!$H$2:$H$6001,A15,Raw_Data!$BJ$2:$BJ$6001,"Due Soon") -> 26 | D15: =COUNTIFS(Raw_Data!$H$2:$H$6001,A15,Raw_Data!$BJ$2:$BJ$6001,"Overdue") -> 2 | E15: =SUMIFS(Raw_Data!$X$2:$X$6001,Raw_Data!$H$2:$H$6001,A15) -> 3685
A16: PUN-L2-M4 | B16: =COUNTIFS(Raw_Data!$H$2:$H$6001,A16,Raw_Data!$BJ$2:$BJ$6001,"Up to Date") -> 96 | C16: =COUNTIFS(Raw_Data!$H$2:$H$6001,A16,Raw_Data!$BJ$2:$BJ$6001,"Due Soon") -> 27 | D16: =COUNTIFS(Raw_Data!$H$2:$H$6001,A16,Raw_Data!$BJ$2:$BJ$6001,"Overdue") -> 3 | E16: =SUMIFS(Raw_Data!$X$2:$X$6001,Raw_Data!$H$2:$H$6001,A16) -> 3611
A17: PUN-L2-M3 | B17: =COUNTIFS(Raw_Data!$H$2:$H$6001,A17,Raw_Data!$BJ$2:$BJ$6001,"Up to Date") -> 93 | C17: =COUNTIFS(Raw_Data!$H$2:$H$6001,A17,Raw_Data!$BJ$2:$BJ$6001,"Due Soon") -> 29 | D17: =COUNTIFS(Raw_Data!$H$2:$H$6001,A17,Raw_Data!$BJ$2:$BJ$6001,"Overdue") -> 1 | E17: =SUMIFS(Raw_Data!$X$2:$X$6001,Raw_Data!$H$2:$H$6001,A17) -> 3607
A18: PUN-L1-M4 | B18: =COUNTIFS(Raw_Data!$H$2:$H$6001,A18,Raw_Data!$BJ$2:$BJ$6001,"Up to Date") -> 77 | C18: =COUNTIFS(Raw_Data!$H$2:$H$6001,A18,Raw_Data!$BJ$2:$BJ$6001,"Due Soon") -> 39 | D18: =COUNTIFS(Raw_Data!$H$2:$H$6001,A18,Raw_Data!$BJ$2:$BJ$6001,"Overdue") -> 6 | E18: =SUMIFS(Raw_Data!$X$2:$X$6001,Raw_Data!$H$2:$H$6001,A18) -> 3595
A19: BLR-L2-M3 | B19: =COUNTIFS(Raw_Data!$H$2:$H$6001,A19,Raw_Data!$BJ$2:$BJ$6001,"Up to Date") -> 100 | C19: =COUNTIFS(Raw_Data!$H$2:$H$6001,A19,Raw_Data!$BJ$2:$BJ$6001,"Due Soon") -> 23 | D19: =COUNTIFS(Raw_Data!$H$2:$H$6001,A19,Raw_Data!$BJ$2:$BJ$6001,"Overdue") -> 0 | E19: =SUMIFS(Raw_Data!$X$2:$X$6001,Raw_Data!$H$2:$H$6001,A19) -> 3577
... A53: NOI-L1-M3 | B53: =COUNTIFS(Raw_Data!$H$2:$H$6001,A53,Raw_Data!$BJ$2:$BJ$6001,"Up to Date") -> 99 | C53: =COUNTIFS(Raw_Data!$H$2:$H$6001,A53,Raw_Data!$BJ$2:$BJ$6001,"Due Soon") -> 21 | D53: =COUNTIFS(Raw_Data!$H$2:$H$6001,A53,Raw_Data!$BJ$2:$BJ$6001,"Overdue") -> 0 | E53: =SUMIFS(Raw_Data!$X$2:$X$6001,Raw_Data!$H$2:$H$6001,A53) -> 2790

Sheet Q5_Supplier_Quality
A1: Which supplier and material grade has the poorest manufacturing quality from Q2 onward?
A4: Raw_Material_Supplier | B4: Defective Units | C4: Weighted Defect Rate
A5: Nova Electronics | B5: =SUMIFS(Raw_Data!$S$2:$S$6001,Raw_Data!$C$2:$C$6001,"<>Q1 2025",Raw_Data!$L$2:$L$6001,A5) -> 4302 | C5: =SUMIFS(Raw_Data!$S$2:$S$6001,Raw_Data!$C$2:$C$6001,"<>Q1 2025",Raw_Data!$L$2:$L$6001,A5)/SUMIFS(Raw_Data!$R$2:$R$6001,Raw_Data!$C$2:$C$6001,"<>Q1 2025",Raw_Data!$L$2:$L$6001,A5) -> 0.058851694
A6: Prime Circuits | B6: =SUMIFS(Raw_Data!$S$2:$S$6001,Raw_Data!$C$2:$C$6001,"<>Q1 2025",Raw_Data!$L$2:$L$6001,A6) -> 1466 | C6: =SUMIFS(Raw_Data!$S$2:$S$6001,Raw_Data!$C$2:$C$6001,"<>Q1 2025",Raw_Data!$L$2:$L$6001,A6)/SUMIFS(Raw_Data!$R$2:$R$6001,Raw_Data!$C$2:$C$6001,"<>Q1 2025",Raw_Data!$L$2:$L$6001,A6) -> 0.023212731
A7: Zenith Parts | B7: =SUMIFS(Raw_Data!$S$2:$S$6001,Raw_Data!$C$2:$C$6001,"<>Q1 2025",Raw_Data!$L$2:$L$6001,A7) -> 1388 | C7: =SUMIFS(Raw_Data!$S$2:$S$6001,Raw_Data!$C$2:$C$6001,"<>Q1 2025",Raw_Data!$L$2:$L$6001,A7)/SUMIFS(Raw_Data!$R$2:$R$6001,Raw_Data!$C$2:$C$6001,"<>Q1 2025",Raw_Data!$L$2:$L$6001,A7) -> 0.024779077
A8: Apex Components | B8: =SUMIFS(Raw_Data!$S$2:$S$6001,Raw_Data!$C$2:$C$6001,"<>Q1 2025",Raw_Data!$L$2:$L$6001,A8) -> 1183 | C8: =SUMIFS(Raw_Data!$S$2:$S$6001,Raw_Data!$C$2:$C$6001,"<>Q1 2025",Raw_Data!$L$2:$L$6001,A8)/SUMIFS(Raw_Data!$R$2:$R$6001,Raw_Data!$C$2:$C$6001,"<>Q1 2025",Raw_Data!$L$2:$L$6001,A8) -> 0.021495021
A12: Nova Electronics | B12: Defective Units | C12: Weighted Defect Rate
A13: Grade B | B13: =SUMIFS(Raw_Data!$S$2:$S$6001,Raw_Data!$C$2:$C$6001,"<>Q1 2025",Raw_Data!$L$2:$L$6001,"Nova Electronics",Raw_Data!$M$2:$M$6001,A13) -> 3429 | C13: =SUMIFS(Raw_Data!$S$2:$S$6001,Raw_Data!$C$2:$C$6001,"<>Q1 2025",Raw_Data!$L$2:$L$6001,"Nova Electronics",Raw_Data!$M$2:$M$6001,A13)/SUMIFS(Raw_Data!$R$2:$R$6001,Raw_Data!$C$2:$C$6001,"<>Q1 2025",Raw_Data!$L$2:$L$6001,"Nova Electronics",Raw_Data!$M$2:$M$6001,A13) -> 0.080502406
A14: Grade A | B14: =SUMIFS(Raw_Data!$S$2:$S$6001,Raw_Data!$C$2:$C$6001,"<>Q1 2025",Raw_Data!$L$2:$L$6001,"Nova Electronics",Raw_Data!$M$2:$M$6001,A14) -> 873 | C14: =SUMIFS(Raw_Data!$S$2:$S$6001,Raw_Data!$C$2:$C$6001,"<>Q1 2025",Raw_Data!$L$2:$L$6001,"Nova Electronics",Raw_Data!$M$2:$M$6001,A14)/SUMIFS(Raw_Data!$R$2:$R$6001,Raw_Data!$C$2:$C$6001,"<>Q1 2025",Raw_Data!$L$2:$L$6001,"Nova Electronics",Raw_Data!$M$2:$M$6001,A14) -> 0.028619197

Sheet Q4_Shipment_Performance
A1: Why did on-time shipment performance deteriorate in Q4?
A3: Quarter | B3: Late Shipment Count
A4: Q1 2025 | B4: 403
A5: Q2 2025 | B5: 395
A6: Q3 2025 | B6: 419
A7: Q4 2025 | B7: 614
B11: Q1 2025 | C11: Q2 2025 | D11: Q3 2025 | E11: Q4 2025
A12: Machine Downtime (Min) | B12: 39952 | C12: 43082 | D12: 43574 | E12: 44106
A13: Worker Absence (Hours) | B13: 6344.7 | C13: 6249.8 | D13: 7015.4 | E13: 6394.1
A14: Overtime (Hours) | B14: 2171.7 | C14: 2310.4 | D14: 2389.7 | E14: 2373.5
A15: Unplanned Breakdown Count | B15: 656 | C15: 951 | D15: 953 | E15: 1002
A18: Q4 Overtime Reasons
A19: Recover Missed Production Target | B19: =COUNTIFS(Raw_Data!$C$2:$C$6001,"Q4 2025",Raw_Data!$AX$2:$AX$6001,A19) -> 725
A20: Extended Quality Rework | B20: =COUNTIFS(Raw_Data!$C$2:$C$6001,"Q4 2025",Raw_Data!$AX$2:$AX$6001,A20) -> 551
A21: Worker Shortage | B21: =COUNTIFS(Raw_Data!$C$2:$C$6001,"Q4 2025",Raw_Data!$AX$2:$AX$6001,A21) -> 153
A22: Recover Lost Production After Breakdown | B22: =COUNTIFS(Raw_Data!$C$2:$C$6001,"Q4 2025",Raw_Data!$AX$2:$AX$6001,A22) -> 51
A23: Normal Schedule | B23: =COUNTIFS(Raw_Data!$C$2:$C$6001,"Q4 2025",Raw_Data!$AX$2:$AX$6001,A23) -> 20
A26: Q4 Shipment Performance by Delay Reason | B26: Shipment Count | C26: Avg Inventory Age (Days | D26: Avg Dispatch Delay (Days) | E26: Avg Transit Delay (Days)
A27: Regional Hub Congestion | B27: =COUNTIFS(Raw_Data!$C$2:$C$6001,"Q4 2025",Raw_Data!$BE$2:$BE$6001,A27) -> 158 | C27: =AVERAGEIFS(Raw_Data!$BA$2:$BA$6001,Raw_Data!$C$2:$C$6001,"Q4 2025",Raw_Data!$BE$2:$BE$6001,A27) -> 16.841772 | D27: =AVERAGEIFS(Raw_Data!$BC$2:$BC$6001,Raw_Data!$C$2:$C$6001,"Q4 2025",Raw_Data!$BE$2:$BE$6001,A27) -> 0.64556962 | E27: =AVERAGEIFS(Raw_Data!$BD$2:$BD$6001,Raw_Data!$C$2:$C$6001,"Q4 2025",Raw_Data!$BE$2:$BE$6001,A27) -> 2.6518987
A28: Carrier Capacity Shortage | B28: =COUNTIFS(Raw_Data!$C$2:$C$6001,"Q4 2025",Raw_Data!$BE$2:$BE$6001,A28) -> 144 | C28: =AVERAGEIFS(Raw_Data!$BA$2:$BA$6001,Raw_Data!$C$2:$C$6001,"Q4 2025",Raw_Data!$BE$2:$BE$6001,A28) -> 17.993056 | D28: =AVERAGEIFS(Raw_Data!$BC$2:$BC$6001,Raw_Data!$C$2:$C$6001,"Q4 2025",Raw_Data!$BE$2:$BE$6001,A28) -> 0.70833333 | E28: =AVERAGEIFS(Raw_Data!$BD$2:$BD$6001,Raw_Data!$C$2:$C$6001,"Q4 2025",Raw_Data!$BE$2:$BE$6001,A28) -> 2.7569444
A29: Factory Dispatch Delay | B29: =COUNTIFS(Raw_Data!$C$2:$C$6001,"Q4 2025",Raw_Data!$BE$2:$BE$6001,A29) -> 136 | C29: =AVERAGEIFS(Raw_Data!$BA$2:$BA$6001,Raw_Data!$C$2:$C$6001,"Q4 2025",Raw_Data!$BE$2:$BE$6001,A29) -> 19.610294 | D29: =AVERAGEIFS(Raw_Data!$BC$2:$BC$6001,Raw_Data!$C$2:$C$6001,"Q4 2025",Raw_Data!$BE$2:$BE$6001,A29) -> 1.2058824 | E29: =AVERAGEIFS(Raw_Data!$BD$2:$BD$6001,Raw_Data!$C$2:$C$6001,"Q4 2025",Raw_Data!$BE$2:$BE$6001,A29) -> 0.029411765
A30: Carrier Transit Delay | B30: =COUNTIFS(Raw_Data!$C$2:$C$6001,"Q4 2025",Raw_Data!$BE$2:$BE$6001,A30) -> 123 | C30: =AVERAGEIFS(Raw_Data!$BA$2:$BA$6001,Raw_Data!$C$2:$C$6001,"Q4 2025",Raw_Data!$BE$2:$BE$6001,A30) -> 18.617886 | D30: =AVERAGEIFS(Raw_Data!$BC$2:$BC$6001,Raw_Data!$C$2:$C$6001,"Q4 2025",Raw_Data!$BE$2:$BE$6001,A30) -> 0.10569106 | E30: =AVERAGEIFS(Raw_Data!$BD$2:$BD$6001,Raw_Data!$C$2:$C$6001,"Q4 2025",Raw_Data!$BE$2:$BE$6001,A30) -> 1.2357724
A31: Customs Clearance Delay | B31: =COUNTIFS(Raw_Data!$C$2:$C$6001,"Q4 2025",Raw_Data!$BE$2:$BE$6001,A31) -> 53 | C31: =AVERAGEIFS(Raw_Data!$BA$2:$BA$6001,Raw_Data!$C$2:$C$6001,"Q4 2025",Raw_Data!$BE$2:$BE$6001,A31) -> 9.9433962 | D31: =AVERAGEIFS(Raw_Data!$BC$2:$BC$6001,Raw_Data!$C$2:$C$6001,"Q4 2025",Raw_Data!$BE$2:$BE$6001,A31) -> 0.52830189 | E31: =AVERAGEIFS(Raw_Data!$BD$2:$BD$6001,Raw_Data!$C$2:$C$6001,"Q4 2025",Raw_Data!$BE$2:$BE$6001,A31) -> 0.86792453
A34: Key Q4 Shipment Delay Drivers
A35: Regional Hub Congestion
A36: Carrier Capacity Shortage
A37: Factory Dispatch Delay
A38: Carrier Transit Delay
A42: Breakdown Reasons for Q4 Delayed Shipments | B42: Shipment Count
A43: No Major Breakdown | B43: =COUNTIFS(Raw_Data!$C$2:$C$6001,"Q4 2025",Raw_Data!$BE$2:$BE$6001,"<>On Time",Raw_Data!$BH$2:$BH$6001,A43) -> 337
A44: Minor Calibration Drift | B44: =COUNTIFS(Raw_Data!$C$2:$C$6001,"Q4 2025",Raw_Data!$BE$2:$BE$6001,"<>On Time",Raw_Data!$BH$2:$BH$6001,A44) -> 105
A45: Short Conveyor Jam | B45: =COUNTIFS(Raw_Data!$C$2:$C$6001,"Q4 2025",Raw_Data!$BE$2:$BE$6001,"<>On Time",Raw_Data!$BH$2:$BH$6001,A45) -> 105
A46: Hydraulic Pressure Failure | B46: =COUNTIFS(Raw_Data!$C$2:$C$6001,"Q4 2025",Raw_Data!$BE$2:$BE$6001,"<>On Time",Raw_Data!$BH$2:$BH$6001,A46) -> 15
A47: Cooling System Failure | B47: =COUNTIFS(Raw_Data!$C$2:$C$6001,"Q4 2025",Raw_Data!$BE$2:$BE$6001,"<>On Time",Raw_Data!$BH$2:$BH$6001,A47) -> 20
A48: Calibration Sensor Failure | B48: =COUNTIFS(Raw_Data!$C$2:$C$6001,"Q4 2025",Raw_Data!$BE$2:$BE$6001,"<>On Time",Raw_Data!$BH$2:$BH$6001,A48) -> 12
A49: Conveyor Jam | B49: =COUNTIFS(Raw_Data!$C$2:$C$6001,"Q4 2025",Raw_Data!$BE$2:$BE$6001,"<>On Time",Raw_Data!$BH$2:$BH$6001,A49) -> 8
A50: Sensor Malfunction | B50: =COUNTIFS(Raw_Data!$C$2:$C$6001,"Q4 2025",Raw_Data!$BE$2:$BE$6001,"<>On Time",Raw_Data!$BH$2:$BH$6001,A50) -> 8
A51: Power Supply Instability | B51: =COUNTIFS(Raw_Data!$C$2:$C$6001,"Q4 2025",Raw_Data!$BE$2:$BE$6001,"<>On Time",Raw_Data!$BH$2:$BH$6001,A51) -> 4

Sheet Q3_Inventory_Buildup
A1: Why did unsold inventory rise sharply in Q4?
A4: Q1 2025 | B4: =SUMIFS(Raw_Data!$V$2:$V$6001, Raw_Data!$C$2:$C$6001,A4) -> 2244
A5: Q2 2025 | B5: =SUMIFS(Raw_Data!$V$2:$V$6001, Raw_Data!$C$2:$C$6001,A5) -> 2498
A6: Q3 2025 | B6: =SUMIFS(Raw_Data!$V$2:$V$6001, Raw_Data!$C$2:$C$6001,A6) -> 2221
A7: Q4 2025 | B7: =SUMIFS(Raw_Data!$V$2:$V$6001, Raw_Data!$C$2:$C$6001,A7) -> 4248
A10: Q4 2025
A11: No Inventory Buildup | B11: =COUNTIFS( Raw_Data!$C$2:$C$6001,"Q4 2025", Raw_Data!$BB$2:$BB$6001,A11 ) -> 601
A12: Production Above Confirmed Demand | B12: =COUNTIFS( Raw_Data!$C$2:$C$6001,"Q4 2025", Raw_Data!$BB$2:$BB$6001,A12 ) -> 447
A13: Order Cancellations | B13: =COUNTIFS( Raw_Data!$C$2:$C$6001,"Q4 2025", Raw_Data!$BB$2:$BB$6001,A13 ) -> 154
A14: Forecast Overestimate and Order Cancellations | B14: =COUNTIFS( Raw_Data!$C$2:$C$6001,"Q4 2025", Raw_Data!$BB$2:$BB$6001,A14 ) -> 112
A15: Slower Customer Release | B15: =COUNTIFS( Raw_Data!$C$2:$C$6001,"Q4 2025", Raw_Data!$BB$2:$BB$6001,A15 ) -> 108
A16: Normal Closing Inventory | B16: =COUNTIFS( Raw_Data!$C$2:$C$6001,"Q4 2025", Raw_Data!$BB$2:$BB$6001,A16 ) -> 78
A19: Production Above Confirmed Demand – Factory
A20: Noida Factory | B20: =COUNTIFS( Raw_Data!$C$2:$C$6001,"Q4 2025", Raw_Data!$BB$2:$BB$6001,"Production Above Confirmed Demand", Raw_Data!$F$2:$F$6001,A20 ) -> 217
A21: Pune Factory | B21: =COUNTIFS( Raw_Data!$C$2:$C$6001,"Q4 2025", Raw_Data!$BB$2:$BB$6001,"Production Above Confirmed Demand", Raw_Data!$F$2:$F$6001,A21 ) -> 69
A22: Bengaluru Factory | B22: =COUNTIFS( Raw_Data!$C$2:$C$6001,"Q4 2025", Raw_Data!$BB$2:$BB$6001,"Production Above Confirmed Demand", Raw_Data!$F$2:$F$6001,A22 ) -> 46
A23: Chennai Factory | B23: =COUNTIFS( Raw_Data!$C$2:$C$6001,"Q4 2025", Raw_Data!$BB$2:$BB$6001,"Production Above Confirmed Demand", Raw_Data!$F$2:$F$6001,A23 ) -> 115
A26: Noida Factory – Product Model
A27: Student Laptop | B27: =COUNTIFS( Raw_Data!$C$2:$C$6001,"Q4 2025", Raw_Data!$BB$2:$BB$6001,"Production Above Confirmed Demand", Raw_Data!$F$2:$F$6001,"Noida Factory", Raw_Data!$J$2:$J$6001,A27 ) -> 112
A28: Business Laptop | B28: =COUNTIFS( Raw_Data!$C$2:$C$6001,"Q4 2025", Raw_Data!$BB$2:$BB$6001,"Production Above Confirmed Demand", Raw_Data!$F$2:$F$6001,"Noida Factory", Raw_Data!$J$2:$J$6001,A28 ) -> 65
A29: Gaming Laptop | B29: =COUNTIFS( Raw_Data!$C$2:$C$6001,"Q4 2025", Raw_Data!$BB$2:$BB$6001,"Production Above Confirmed Demand", Raw_Data!$F$2:$F$6001,"Noida Factory", Raw_Data!$J$2:$J$6001,A29 ) -> 40
B32: Confirmed Order Units | C32: Planned Units | D32: Units Made | E32: Defective Units | F32: Good Units | G32: Units Sold | H32: Unsold Units | I32: Weighted Defect Rate
A33: Student Laptop | B33: =SUMIFS(Raw_Data!$P$2:$P$6001,Raw_Data!$C$2:$C$6001,"Q4 2025",Raw_Data!$BB$2:$BB$6001,"Production Above Confirmed Demand",Raw_Data!$F$2:$F$6001,"Noida Factory",Raw_Data!$J$2:$J$6001,"Student Laptop") -> 6602 | C33: =SUMIFS(Raw_Data!$Q$2:$Q$6001,Raw_Data!$C$2:$C$6001,"Q4 2025",Raw_Data!$BB$2:$BB$6001,"Production Above Confirmed Demand",Raw_Data!$F$2:$F$6001,"Noida Factory",Raw_Data!$J$2:$J$6001,"Student Laptop") -> 6904 | D33: =SUMIFS(Raw_Data!$R$2:$R$6001,Raw_Data!$C$2:$C$6001,"Q4 2025",Raw_Data!$BB$2:$BB$6001,"Production Above Confirmed Demand",Raw_Data!$F$2:$F$6001,"Noida Factory",Raw_Data!$J$2:$J$6001,"Student Laptop") -> 7048 | E33: =SUMIFS(Raw_Data!$S$2:$S$6001,Raw_Data!$C$2:$C$6001,"Q4 2025",Raw_Data!$BB$2:$BB$6001,"Production Above Confirmed Demand",Raw_Data!$F$2:$F$6001,"Noida Factory",Raw_Data!$J$2:$J$6001,"Student Laptop") -> 148 | F33: =SUMIFS(Raw_Data!$T$2:$T$6001,Raw_Data!$C$2:$C$6001,"Q4 2025",Raw_Data!$BB$2:$BB$6001,"Production Above Confirmed Demand",Raw_Data!$F$2:$F$6001,"Noida Factory",Raw_Data!$J$2:$J$6001,"Student Laptop") -> 6900 | G33: =SUMIFS(Raw_Data!$U$2:$U$6001,Raw_Data!$C$2:$C$6001,"Q4 2025",Raw_Data!$BB$2:$BB$6001,"Production Above Confirmed Demand",Raw_Data!$F$2:$F$6001,"Noida Factory",Raw_Data!$J$2:$J$6001,"Student Laptop") -> 6439 | H33: =SUMIFS(Raw_Data!$V$2:$V$6001,Raw_Data!$C$2:$C$6001,"Q4 2025",Raw_Data!$BB$2:$BB$6001,"Production Above Confirmed Demand",Raw_Data!$F$2:$F$6001,"Noida Factory",Raw_Data!$J$2:$J$6001,"Student Laptop") -> 461 | I33: =SUMIFS(Raw_Data!$S$2:$S$6001,Raw_Data!$C$2:$C$6001,"Q4 2025",Raw_Data!$BB$2:$BB$6001,"Production Above Confirmed Demand",Raw_Data!$F$2:$F$6001,"Noida Factory",Raw_Data!$J$2:$J$6001,"Student Laptop") / SUMIFS(Raw_Data!$R$2:$R$6001,Raw_Data!$C$2:$C$6001,"Q4 2025",Raw_Data!$BB$2:$BB$6001,"Production Above Confirmed Demand",Raw_Data!$F$2:$F$6001,"Noida Factory",Raw_Data!$J$2:$J$6001,"Student Laptop") -> 0.020998865
A39: Confirmed_Order_Units | B39: Units_Made | C39: Demand Forecast Units
A40: =SUMIFS(Raw_Data!$P$2:$P$6001,Raw_Data!$C$2:$C$6001,"Q4 2025",Raw_Data!$BB$2:$BB$6001,"Production Above Confirmed Demand",Raw_Data!$F$2:$F$6001,"Noida Factory",Raw_Data!$J$2:$J$6001,"Student Laptop") -> 6602 | B40: =SUMIFS(Raw_Data!$R$2:$R$6001,Raw_Data!$C$2:$C$6001,"Q4 2025",Raw_Data!$BB$2:$BB$6001,"Production Above Confirmed Demand",Raw_Data!$F$2:$F$6001,"Noida Factory",Raw_Data!$J$2:$J$6001,"Student Laptop") -> 7048 | C40: =SUMIFS(Raw_Data!$AY$2:$AY$6001,Raw_Data!$C$2:$C$6001,"Q4 2025",Raw_Data!$BB$2:$BB$6001,"Production Above Confirmed Demand",Raw_Data!$F$2:$F$6001,"Noida Factory",Raw_Data!$J$2:$J$6001,"Student Laptop") -> 6780
A42: Production Above Confirmed Orders % | B42: =(B40-A40)/A40 -> 0.067555286
A43: Production Above Demand Forecast % | B43: =(B40-C40)/C40 -> 0.039528024

Sheet Q2_Warranty_Cost
A1: Why did warranty cost explode for Business Laptop batches from Chennai Factory Line 1 in Q3?
A4: Quarter | B4: Warranty Cost | C4: Warranty Claims Units
A5: Q2 2025 | B5: =SUMIFS(Raw_Data!$AK$2:$AK$6001,Raw_Data!$C$2:$C$6001,"Q2 2025",Raw_Data!$F$2:$F$6001,"Chennai Factory",Raw_Data!$G$2:$G$6001,"Line 1",Raw_Data!$J$2:$J$6001,"Business Laptop") -> 95394.03 | C5: =SUMIFS(Raw_Data!$AJ$2:$AJ$6001,Raw_Data!$C$2:$C$6001,"Q2 2025",Raw_Data!$F$2:$F$6001,"Chennai Factory",Raw_Data!$G$2:$G$6001,"Line 1",Raw_Data!$J$2:$J$6001,"Business Laptop") -> 7
A6: Q3 2025 | B6: =SUMIFS(Raw_Data!$AK$2:$AK$6001,Raw_Data!$C$2:$C$6001,"Q3 2025",Raw_Data!$F$2:$F$6001,"Chennai Factory",Raw_Data!$G$2:$G$6001,"Line 1",Raw_Data!$J$2:$J$6001,"Business Laptop") -> 1223616.4 | C6: =SUMIFS(Raw_Data!$AJ$2:$AJ$6001,Raw_Data!$C$2:$C$6001,"Q3 2025",Raw_Data!$F$2:$F$6001,"Chennai Factory",Raw_Data!$G$2:$G$6001,"Line 1",Raw_Data!$J$2:$J$6001,"Business Laptop") -> 89
A8: Warranty Cost Change % | B8: =(B6-B5)/B5 -> 11.826971
A10: Warranty Failure Type
A11: Battery Performance Failure | B11: =COUNTIFS( Raw_Data!$C$2:$C$6001,"Q3 2025", Raw_Data!$F$2:$F$6001,"Chennai Factory", Raw_Data!$G$2:$G$6001,"Line 1", Raw_Data!$J$2:$J$6001,"Business Laptop", Raw_Data!$AU$2:$AU$6001,A11 ) -> 21
A12: Power Failure | B12: =COUNTIFS( Raw_Data!$C$2:$C$6001,"Q3 2025", Raw_Data!$F$2:$F$6001,"Chennai Factory", Raw_Data!$G$2:$G$6001,"Line 1", Raw_Data!$J$2:$J$6001,"Business Laptop", Raw_Data!$AU$2:$AU$6001,A12 ) -> 10
A13: Random Shutdown | B13: =COUNTIFS( Raw_Data!$C$2:$C$6001,"Q3 2025", Raw_Data!$F$2:$F$6001,"Chennai Factory", Raw_Data!$G$2:$G$6001,"Line 1", Raw_Data!$J$2:$J$6001,"Business Laptop", Raw_Data!$AU$2:$AU$6001,A13 ) -> 6
A14: No Warranty Claim | B14: =COUNTIFS( Raw_Data!$C$2:$C$6001,"Q3 2025", Raw_Data!$F$2:$F$6001,"Chennai Factory", Raw_Data!$G$2:$G$6001,"Line 1", Raw_Data!$J$2:$J$6001,"Business Laptop", Raw_Data!$AU$2:$AU$6001,A14 ) -> 5
A15: Storage Failure | B15: =COUNTIFS( Raw_Data!$C$2:$C$6001,"Q3 2025", Raw_Data!$F$2:$F$6001,"Chennai Factory", Raw_Data!$G$2:$G$6001,"Line 1", Raw_Data!$J$2:$J$6001,"Business Laptop", Raw_Data!$AU$2:$AU$6001,A15 ) -> 1
A18: Failed Component – Battery Performance Failure
A19: Battery Cell | B19: =COUNTIFS( Raw_Data!$C$2:$C$6001,"Q3 2025", Raw_Data!$F$2:$F$6001,"Chennai Factory", Raw_Data!$G$2:$G$6001,"Line 1", Raw_Data!$J$2:$J$6001,"Business Laptop", Raw_Data!$AU$2:$AU$6001,"Battery Performance Failure", Raw_Data!$AV$2:$AV$6001,A19 ) -> 21
A22: Warranty Root Cause
A23: Latent Supplier Component Defect | B23: =COUNTIFS( Raw_Data!$C$2:$C$6001,"Q3 2025", Raw_Data!$F$2:$F$6001,"Chennai Factory", Raw_Data!$G$2:$G$6001,"Line 1", Raw_Data!$J$2:$J$6001,"Business Laptop", Raw_Data!$AU$2:$AU$6001,"Battery Performance Failure", Raw_Data!$AV$2:$AV$6001,"Battery Cell", Raw_Data!$AW$2:$AW$6001,A23 ) -> 21
A26: Supplier – Latent Supplier Component Defect
A27: Prime Circuits | B27: =COUNTIFS( Raw_Data!$C$2:$C$6001,"Q3 2025", Raw_Data!$F$2:$F$6001,"Chennai Factory", Raw_Data!$G$2:$G$6001,"Line 1", Raw_Data!$J$2:$J$6001,"Business Laptop", Raw_Data!$AU$2:$AU$6001,"Battery Performance Failure", Raw_Data!$AV$2:$AV$6001,"Battery Cell", Raw_Data!$AW$2:$AW$6001,"Latent Supplier Component Defect", Raw_Data!$L$2:$L$6001,A27 ) -> 21
A28: Apex Components | B28: =COUNTIFS( Raw_Data!$C$2:$C$6001,"Q3 2025", Raw_Data!$F$2:$F$6001,"Chennai Factory", Raw_Data!$G$2:$G$6001,"Line 1", Raw_Data!$J$2:$J$6001,"Business Laptop", Raw_Data!$AU$2:$AU$6001,"Battery Performance Failure", Raw_Data!$AV$2:$AV$6001,"Battery Cell", Raw_Data!$AW$2:$AW$6001,"Latent Supplier Component Defect", Raw_Data!$L$2:$L$6001,A28 ) -> 0
A29: Zenith Parts | B29: =COUNTIFS( Raw_Data!$C$2:$C$6001,"Q3 2025", Raw_Data!$F$2:$F$6001,"Chennai Factory", Raw_Data!$G$2:$G$6001,"Line 1", Raw_Data!$J$2:$J$6001,"Business Laptop", Raw_Data!$AU$2:$AU$6001,"Battery Performance Failure", Raw_Data!$AV$2:$AV$6001,"Battery Cell", Raw_Data!$AW$2:$AW$6001,"Latent Supplier Component Defect", Raw_Data!$L$2:$L$6001,A29 ) -> 0
A30: Nova Electronics | B30: =COUNTIFS( Raw_Data!$C$2:$C$6001,"Q3 2025", Raw_Data!$F$2:$F$6001,"Chennai Factory", Raw_Data!$G$2:$G$6001,"Line 1", Raw_Data!$J$2:$J$6001,"Business Laptop", Raw_Data!$AU$2:$AU$6001,"Battery Performance Failure", Raw_Data!$AV$2:$AV$6001,"Battery Cell", Raw_Data!$AW$2:$AW$6001,"Latent Supplier Component Defect", Raw_Data!$L$2:$L$6001,A30 ) -> 0
A33: Prime Circuits | B33: Material Grade from Prime Circuits
A34: Grade A | B34: =COUNTIFS( Raw_Data!$C$2:$C$6001,"Q3 2025", Raw_Data!$F$2:$F$6001,"Chennai Factory", Raw_Data!$G$2:$G$6001,"Line 1", Raw_Data!$J$2:$J$6001,"Business Laptop", Raw_Data!$AU$2:$AU$6001,"Battery Performance Failure", Raw_Data!$AV$2:$AV$6001,"Battery Cell", Raw_Data!$AW$2:$AW$6001,"Latent Supplier Component Defect", Raw_Data!$L$2:$L$6001,"Prime Circuits", Raw_Data!$M$2:$M$6001,A34 ) -> 17
A35: Grade B | B35: =COUNTIFS( Raw_Data!$C$2:$C$6001,"Q3 2025", Raw_Data!$F$2:$F$6001,"Chennai Factory", Raw_Data!$G$2:$G$6001,"Line 1", Raw_Data!$J$2:$J$6001,"Business Laptop", Raw_Data!$AU$2:$AU$6001,"Battery Performance Failure", Raw_Data!$AV$2:$AV$6001,"Battery Cell", Raw_Data!$AW$2:$AW$6001,"Latent Supplier Component Defect", Raw_Data!$L$2:$L$6001,"Prime Circuits", Raw_Data!$M$2:$M$6001,A35 ) -> 4
A37: Machine | B37: Grade A Failure Cases | C37: Warranty Cost
A38: CHE-L1-M2 | B38: =COUNTIFS( Raw_Data!$C$2:$C$6001,"Q3 2025", Raw_Data!$F$2:$F$6001,"Chennai Factory", Raw_Data!$G$2:$G$6001,"Line 1", Raw_Data!$J$2:$J$6001,"Business Laptop", Raw_Data!$AU$2:$AU$6001,"Battery Performance Failure", Raw_Data!$AV$2:$AV$6001,"Battery Cell", Raw_Data!$AW$2:$AW$6001,"Latent Supplier Component Defect", Raw_Data!$L$2:$L$6001,"Prime Circuits", Raw_Data!$M$2:$M$6001,"Grade A", Raw_Data!$H$2:$H$6001,A38 ) -> 5 | C38: =SUMIFS( Raw_Data!$AK$2:$AK$6001, Raw_Data!$C$2:$C$6001,"Q3 2025", Raw_Data!$F$2:$F$6001,"Chennai Factory", Raw_Data!$G$2:$G$6001,"Line 1", Raw_Data!$J$2:$J$6001,"Business Laptop", Raw_Data!$AU$2:$AU$6001,"Battery Performance Failure", Raw_Data!$AV$2:$AV$6001,"Battery Cell", Raw_Data!$AW$2:$AW$6001,"Latent Supplier Component Defect", Raw_Data!$L$2:$L$6001,"Prime Circuits", Raw_Data!$M$2:$M$6001,"Grade A", Raw_Data!$H$2:$H$6001,A38 ) -> 188817.74
A39: CHE-L1-M4 | B39: =COUNTIFS( Raw_Data!$C$2:$C$6001,"Q3 2025", Raw_Data!$F$2:$F$6001,"Chennai Factory", Raw_Data!$G$2:$G$6001,"Line 1", Raw_Data!$J$2:$J$6001,"Business Laptop", Raw_Data!$AU$2:$AU$6001,"Battery Performance Failure", Raw_Data!$AV$2:$AV$6001,"Battery Cell", Raw_Data!$AW$2:$AW$6001,"Latent Supplier Component Defect", Raw_Data!$L$2:$L$6001,"Prime Circuits", Raw_Data!$M$2:$M$6001,"Grade A", Raw_Data!$H$2:$H$6001,A39 ) -> 5 | C39: =SUMIFS( Raw_Data!$AK$2:$AK$6001, Raw_Data!$C$2:$C$6001,"Q3 2025", Raw_Data!$F$2:$F$6001,"Chennai Factory", Raw_Data!$G$2:$G$6001,"Line 1", Raw_Data!$J$2:$J$6001,"Business Laptop", Raw_Data!$AU$2:$AU$6001,"Battery Performance Failure", Raw_Data!$AV$2:$AV$6001,"Battery Cell", Raw_Data!$AW$2:$AW$6001,"Latent Supplier Component Defect", Raw_Data!$L$2:$L$6001,"Prime Circuits", Raw_Data!$M$2:$M$6001,"Grade A", Raw_Data!$H$2:$H$6001,A39 ) -> 141356.24
A40: CHE-L1-M1 | B40: =COUNTIFS( Raw_Data!$C$2:$C$6001,"Q3 2025", Raw_Data!$F$2:$F$6001,"Chennai Factory", Raw_Data!$G$2:$G$6001,"Line 1", Raw_Data!$J$2:$J$6001,"Business Laptop", Raw_Data!$AU$2:$AU$6001,"Battery Performance Failure", Raw_Data!$AV$2:$AV$6001,"Battery Cell", Raw_Data!$AW$2:$AW$6001,"Latent Supplier Component Defect", Raw_Data!$L$2:$L$6001,"Prime Circuits", Raw_Data!$M$2:$M$6001,"Grade A", Raw_Data!$H$2:$H$6001,A40 ) -> 3 | C40: =SUMIFS( Raw_Data!$AK$2:$AK$6001, Raw_Data!$C$2:$C$6001,"Q3 2025", Raw_Data!$F$2:$F$6001,"Chennai Factory", Raw_Data!$G$2:$G$6001,"Line 1", Raw_Data!$J$2:$J$6001,"Business Laptop", Raw_Data!$AU$2:$AU$6001,"Battery Performance Failure", Raw_Data!$AV$2:$AV$6001,"Battery Cell", Raw_Data!$AW$2:$AW$6001,"Latent Supplier Component Defect", Raw_Data!$L$2:$L$6001,"Prime Circuits", Raw_Data!$M$2:$M$6001,"Grade A", Raw_Data!$H$2:$H$6001,A40 ) -> 96097.61
A41: CHE-L1-M3 | B41: =COUNTIFS( Raw_Data!$C$2:$C$6001,"Q3 2025", Raw_Data!$F$2:$F$6001,"Chennai Factory", Raw_Data!$G$2:$G$6001,"Line 1", Raw_Data!$J$2:$J$6001,"Business Laptop", Raw_Data!$AU$2:$AU$6001,"Battery Performance Failure", Raw_Data!$AV$2:$AV$6001,"Battery Cell", Raw_Data!$AW$2:$AW$6001,"Latent Supplier Component Defect", Raw_Data!$L$2:$L$6001,"Prime Circuits", Raw_Data!$M$2:$M$6001,"Grade A", Raw_Data!$H$2:$H$6001,A41 ) -> 4 | C41: =SUMIFS( Raw_Data!$AK$2:$AK$6001, Raw_Data!$C$2:$C$6001,"Q3 2025", Raw_Data!$F$2:$F$6001,"Chennai Factory", Raw_Data!$G$2:$G$6001,"Line 1", Raw_Data!$J$2:$J$6001,"Business Laptop", Raw_Data!$AU$2:$AU$6001,"Battery Performance Failure", Raw_Data!$AV$2:$AV$6001,"Battery Cell", Raw_Data!$AW$2:$AW$6001,"Latent Supplier Component Defect", Raw_Data!$L$2:$L$6001,"Prime Circuits", Raw_Data!$M$2:$M$6001,"Grade A", Raw_Data!$H$2:$H$6001,A41 ) -> 138726.17

Sheet Q1_Profit_Decline
A1: Why did Q2 operating profit fall even though production increased?
A3: Quarter | B3: Units Made | C3: Sales Revenue | D3: Operating Cost | E3: Operating Profit
A4: Q1 2025 | B4: =SUMIF(Raw_Data!$C$2:$C$6001,$A4,Raw_Data!$R$2:$R$6001) -> 78076 | C4: =SUMIF(Raw_Data!$C$2:$C$6001,$A4,Raw_Data!$AB$2:$AB$6001) -> 3.4877457e+09 | D4: =SUMIF(Raw_Data!$C$2:$C$6001,$A4,Raw_Data!$AR$2:$AR$6001) -> 2.7655898e+09 | E4: =SUMIF(Raw_Data!$C$2:$C$6001,$A4,Raw_Data!$AS$2:$AS$6001) -> 7.2215593e+08
A5: Q2 2025 | B5: =SUMIF(Raw_Data!$C$2:$C$6001,$A5,Raw_Data!$R$2:$R$6001) -> 93691 | C5: =SUMIF(Raw_Data!$C$2:$C$6001,$A5,Raw_Data!$AB$2:$AB$6001) -> 3.7322715e+09 | D5: =SUMIF(Raw_Data!$C$2:$C$6001,$A5,Raw_Data!$AR$2:$AR$6001) -> 3.1112174e+09 | E5: =SUMIF(Raw_Data!$C$2:$C$6001,$A5,Raw_Data!$AS$2:$AS$6001) -> 6.210541e+08
A8: Sales Revenue Growth % | B8: =(C5-C4)/C4 -> 0.070109983
A9: Operating Cost Growth % | B9: =(D5-D4)/D4 -> 0.12497429
A11: Production Growth % | B11: =(B5-B4)/B4 -> 0.19999744
A12: Operating Profit Change % | B12: =(E5-E4)/E4 -> -0.14
A15: Factory | B15: Total Negative Operating Profit
A16: Noida Factory | B16: =SUMIFS(Raw_Data!$AS$2:$AS$6001, Raw_Data!$C$2:$C$6001,"Q2 2025", Raw_Data!$F$2:$F$6001,A16, Raw_Data!$AS$2:$AS$6001,"<0") -> -1205513.9
A17: Chennai Factory | B17: =SUMIFS(Raw_Data!$AS$2:$AS$6001, Raw_Data!$C$2:$C$6001,"Q2 2025", Raw_Data!$F$2:$F$6001,A17, Raw_Data!$AS$2:$AS$6001,"<0") -> -725383.96
A18: Pune Factory | B18: =SUMIFS(Raw_Data!$AS$2:$AS$6001, Raw_Data!$C$2:$C$6001,"Q2 2025", Raw_Data!$F$2:$F$6001,A18, Raw_Data!$AS$2:$AS$6001,"<0") -> -294704.82
A19: Bengaluru Factory | B19: =SUMIFS(Raw_Data!$AS$2:$AS$6001, Raw_Data!$C$2:$C$6001,"Q2 2025", Raw_Data!$F$2:$F$6001,A19, Raw_Data!$AS$2:$AS$6001,"<0") -> -6966.15
A22: Noida Factory | B22: Total Negative Operating Profit
A23: Line 1 | B23: =SUMIFS(Raw_Data!$AS$2:$AS$6001, Raw_Data!$C$2:$C$6001,"Q2 2025", Raw_Data!$F$2:$F$6001,"Noida Factory", Raw_Data!$G$2:$G$6001,"Line 1", Raw_Data!$AS$2:$AS$6001,"<0") -> -339295.73
A24: Line 2 | B24: =SUMIFS(Raw_Data!$AS$2:$AS$6001, Raw_Data!$C$2:$C$6001,"Q2 2025", Raw_Data!$F$2:$F$6001,"Noida Factory", Raw_Data!$G$2:$G$6001,"Line 2", Raw_Data!$AS$2:$AS$6001,"<0") -> -307384.63
A25: Line 3 | B25: =SUMIFS(Raw_Data!$AS$2:$AS$6001, Raw_Data!$C$2:$C$6001,"Q2 2025", Raw_Data!$F$2:$F$6001,"Noida Factory", Raw_Data!$G$2:$G$6001,"Line 3", Raw_Data!$AS$2:$AS$6001,"<0") -> -558833.57
A27: Noida Factory - Line 3
A28: Raw Material Supplier | B28: Total Negative Operating Profit
A29: Apex Components | B29: =SUMIFS(Raw_Data!$AS$2:$AS$6001,Raw_Data!$C$2:$C$6001,"Q2 2025",Raw_Data!$F$2:$F$6001,"Noida Factory",Raw_Data!$G$2:$G$6001,"Line 3",Raw_Data!$L$2:$L$6001,A29,Raw_Data!$AS$2:$AS$6001,"<0") -> -460867.21
A30: Prime Circuits | B30: =SUMIFS(Raw_Data!$AS$2:$AS$6001,Raw_Data!$C$2:$C$6001,"Q2 2025",Raw_Data!$F$2:$F$6001,"Noida Factory",Raw_Data!$G$2:$G$6001,"Line 3",Raw_Data!$L$2:$L$6001,A30,Raw_Data!$AS$2:$AS$6001,"<0") -> 0
A31: Nova Electronics | B31: =SUMIFS(Raw_Data!$AS$2:$AS$6001,Raw_Data!$C$2:$C$6001,"Q2 2025",Raw_Data!$F$2:$F$6001,"Noida Factory",Raw_Data!$G$2:$G$6001,"Line 3",Raw_Data!$L$2:$L$6001,A31,Raw_Data!$AS$2:$AS$6001,"<0") -> 0
A34: Material Grade | B34: Total Negative Operating Profit
A35: Grade A | B35: =SUMIFS(Raw_Data!$AS$2:$AS$6001, Raw_Data!$C$2:$C$6001,"Q2 2025", Raw_Data!$F$2:$F$6001,"Noida Factory", Raw_Data!$G$2:$G$6001,"Line 3", Raw_Data!$L$2:$L$6001,"Apex Components", Raw_Data!$M$2:$M$6001,"Grade A", Raw_Data!$AS$2:$AS$6001,"<0") -> -460867.21
A36: Grade B | B36: =SUMIFS(Raw_Data!$AS$2:$AS$6001,Raw_Data!$C$2:$C$6001,"Q2 2025",Raw_Data!$F$2:$F$6001,"Noida Factory",Raw_Data!$G$2:$G$6001,"Line 3",Raw_Data!$L$2:$L$6001,"Apex Components",Raw_Data!$M$2:$M$6001,"Grade B",Raw_Data!$AS$2:$AS$6001,"<0") -> 0
A41: Apex Components
A42: Grade A
B43: Weighted Defect Rate
B44: =SUMIFS(Raw_Data!$S$2:$S$6001,Raw_Data!$C$2:$C$6001,"Q2 2025",Raw_Data!$F$2:$F$6001,"Noida Factory",Raw_Data!$G$2:$G$6001,"Line 3",Raw_Data!$L$2:$L$6001,"Apex Components",Raw_Data!$M$2:$M$6001,"Grade A")/SUMIFS(Raw_Data!$R$2:$R$6001,Raw_Data!$C$2:$C$6001,"Q2 2025",Raw_Data!$F$2:$F$6001,"Noida Factory",Raw_Data!$G$2:$G$6001,"Line 3",Raw_Data!$L$2:$L$6001,"Apex Components",Raw_Data!$M$2:$M$6001,"Grade A") -> 0.017521902
C46: Avg Machine Downtime (Min) | D46: Avg Worker Absence (Hours)
A47: Destination Region | B47: Total Negative Operating Profit | C47: =AVERAGEIFS(Raw_Data!$X$2:$X$6001,Raw_Data!$C$2:$C$6001,"Q2 2025",Raw_Data!$F$2:$F$6001,"Noida Factory",Raw_Data!$G$2:$G$6001,"Line 3",Raw_Data!$L$2:$L$6001,"Apex Components",Raw_Data!$M$2:$M$6001,"Grade A") -> 22.583333 | D47: =AVERAGEIFS(Raw_Data!$Y$2:$Y$6001, Raw_Data!$C$2:$C$6001,"Q2 2025", Raw_Data!$F$2:$F$6001,"Noida Factory", Raw_Data!$G$2:$G$6001,"Line 3", Raw_Data!$L$2:$L$6001,"Apex Components", Raw_Data!$M$2:$M$6001,"Grade A") -> 3.8083333
A48: Export | B48: =SUMIFS(Raw_Data!$AS$2:$AS$6001,Raw_Data!$C$2:$C$6001,"Q2 2025",Raw_Data!$F$2:$F$6001,"Noida Factory",Raw_Data!$G$2:$G$6001,"Line 3",Raw_Data!$L$2:$L$6001,"Apex Components",Raw_Data!$M$2:$M$6001,"Grade A",Raw_Data!$N$2:$N$6001,A48,Raw_Data!$AS$2:$AS$6001,"<0") -> -207468.14
A49: North | B49: =SUMIFS(Raw_Data!$AS$2:$AS$6001,Raw_Data!$C$2:$C$6001,"Q2 2025",Raw_Data!$F$2:$F$6001,"Noida Factory",Raw_Data!$G$2:$G$6001,"Line 3",Raw_Data!$L$2:$L$6001,"Apex Components",Raw_Data!$M$2:$M$6001,"Grade A",Raw_Data!$N$2:$N$6001,A49,Raw_Data!$AS$2:$AS$6001,"<0") -> -137552.82
A50: South | B50: =SUMIFS(Raw_Data!$AS$2:$AS$6001,Raw_Data!$C$2:$C$6001,"Q2 2025",Raw_Data!$F$2:$F$6001,"Noida Factory",Raw_Data!$G$2:$G$6001,"Line 3",Raw_Data!$L$2:$L$6001,"Apex Components",Raw_Data!$M$2:$M$6001,"Grade A",Raw_Data!$N$2:$N$6001,A50,Raw_Data!$AS$2:$AS$6001,"<0") -> -78391.85

Sheet Executive_Dashboard
B1: Q1 2025 | C1: Q2 2025 | G1: Quarter | H1: Q2 2025 | I1: Q3 2025 | O1: Q1 2025 | P1: 403
A2: Units Made | B2: 78076 | C2: 93691 | G2: Warranty Cost | H2: 95394.03 | I2: 1223616.4 | L2: Q1 2025 | M2: 2244 | O2: Q2 2025 | P2: 395
A3: Operating Profit | B3: 7.2215593e+08 | C3: 6.210541e+08 | G3: Warranty Claims Units | H3: 7 | I3: 89 | L3: Q2 2025 | M3: 2498 | O3: Q3 2025 | P3: 419
L4: Q3 2025 | M4: 2221 | O4: Q4 2025 | P4: 614
J5: Q4 2025 | K5: 4248
G18: Machine | H18: Warranty Cost | O18: Q4 Shipment Performance by Delay Reason | P18: Shipment Count
A19: Metric | B19: Growth | G19: CHE-L1-M2 | H19: 188817.74 | L19: No Inventory Buildup | M19: 601 | O19: Regional Hub Congestion | P19: 158
A20: Sales Revenue | B20: 0.0701 | G20: CHE-L1-M4 | H20: 141356.24 | L20: Production Above Confirmed Demand | M20: 447 | O20: Carrier Capacity Shortage | P20: 144
A21: Operating Cost | B21: 0.125 | G21: CHE-L1-M1 | H21: 96097.61 | L21: Order Cancellations | M21: 154 | O21: Factory Dispatch Delay | P21: 136
G22: CHE-L1-M3 | H22: 138726.17 | L22: Forecast Overestimate and Order Cancellations | M22: 112 | O22: Carrier Transit Delay | P22: 123
L23: Slower Customer Release | M23: 108 | O23: Customs Clearance Delay | P23: 53
L24: Normal Closing Inventory | M24: 78
A33: Q1 – Executive Summary | F33: Q2 – Executive Summary | K33: Q3 – Executive Summary | O33: Q4 – Executive Summary
F35: KEY FINDING | K35: KEY FINDING | O35: KEY FINDING
A36: KEY FINDING | F36: Q3 warranty cost increased from ₹95,394 to ₹12.24 lakh (+1,182.7%), while warranty claims increased from 7 to 89. Battery Performance Failure was the leading failure type, with 21 cases. | K36: Q4 unsold inventory increased sharply to 4,248 units, up from 2,221 units in Q3 (+91%). The largest identified Q4 inventory driver was production above confirmed demand (447 cases), followed by order cancellations (154) and forecast overestimation/order cancellations (112). | O36: Late shipments increased sharply to 614 in Q4, compared with 419 in Q3 (+46.5%). The main shipment-delay categories were Regional Hub Congestion (158), Carrier Capacity Shortage (144), Factory Dispatch Delay (136), and Carrier Transit Delay (123). Q4 also recorded the highest unplanned breakdown count at 1,002.
A37: Q2 production increased by 20.0%, but operating profit declined by 14.0%. Sales revenue grew by only 7.01%, while operating costs increased by 12.50%, indicating significant margin pressure.
F42: CONCLUSION | K42: CONCLUSION
A43: CONCLUSION | F43: The investigation traces the issue to Battery Cells, with Latent Supplier Component Defect identified as the root cause. All 21 identified cases were linked to Prime Circuits, with Grade A material accounting for 17 cases. | K43: The Q4 inventory increase was driven primarily by a production–demand mismatch, with excess production compounded by cancellations and forecasting issues. The supporting analysis points particularly to Noida Factory and Student Laptop production as an important contributor. | O43: CONCLUSION
A44: The Q2 profit decline was primarily driven by operating costs growing faster than sales revenue, despite the increase in production. Negative-profit batches, particularly at Noida Factory, were an additional localized issue rather than the main cause of the overall decline. | O44: Q4's deterioration in on-time shipment performance was driven by a combination of logistics constraints and production disruption, rather than one isolated issue. Regional/carrier delays were significant, while high breakdown activity and overtime associated with recovering missed production targets and quality rework indicate additional operational pressure.
F49: RECOMMENDATION | K49: RECOMMENDATION
A50: RECOMMENDATION | F50: Prioritize a supplier-quality investigation of Prime Circuits Grade A battery-cell components. Begin corrective action with CHE-L1-M2, which recorded the highest warranty cost among the Chennai Line 1 machines, while checking the remaining Line 1 machines for the same component defect. | K50: Tighten production planning against confirmed orders and demand forecasts, with priority review of Noida Factory’s Student Laptop production. Introduce earlier controls for overproduction and order cancellations to prevent excess finished inventory from accumulating in future quarters. | O50: RECOMMENDATION
A51: Prioritize cost-control initiatives and investigate the major operating-cost drivers behind Q2's 12.50% increase. Separately review Noida Factory's negative-profit batches to address localized inefficiencies. | O51: Prioritize carrier and regional-hub capacity planning, improve factory dispatch coordination, and reduce production disruption through stronger preventive maintenance. Management should also address the causes of missed production targets and quality rework to reduce dependence on overtime and protect shipment schedules.
A61: Raw_Material_Supplier | B61: Defective Units | F61: Machine | G61: Overdue | H61: Due Soon
A62: Nova Electronics | B62: 4302 | F62: PUN-L3-M3 | G62: 97 | H62: 6 | P62: Factory | Q62: Total Safety Incidents
A63: Prime Circuits | B63: 1466 | F63: PUN-L3-M4 | G63: 99 | H63: 12 | P63: Chennai Factory | Q63: 13
A64: Zenith Parts | B64: 1388 | F64: BLR-L2-M2 | G64: 96 | H64: 7 | K64: Shift | L64: Weighted Defect Rate | M64: Avg Machine Downtime (Min) | P64: Noida Factory | Q64: 7
A65: Apex Components | B65: 1183 | K65: Night | L65: 0.034929983 | M65: 35.176 | P65: Pune Factory | Q65: 18
K66: Morning | L66: 0.029602528 | M66: 23.302 | P66: Bengaluru Factory | Q66: 21
K67: Evening | L67: 0.030381562 | M67: 26.879
A80: Nova Electronics | B80: Defective Units
A81: Grade B | B81: 3429
A82: Grade A | B82: 873
P83: Factory | Q83: Defect Rate | R83: Machine Downtime (Min)
P84: Chennai Factory | Q84: 0.024955305 | R84: 26.725753
K85: Factory | L85: Weighted Defect Rate | M85: Machine_Downtime (Min) | P85: Noida Factory | Q85: 0.021319617 | R85: 23.247354
G86: Machine | H86: Total Machine Downtime (Min) | K86: Pune Factory | L86: 0.044439345 | M86: 46.208925 | P86: Pune Factory | Q86: 0.040054835 | R86: 33.167001
G87: PUN-L3-M3 | H87: 7139 | K87: Chennai Factory | L87: 0.027542529 | M87: 30.215842 | P87: Bengaluru Factory | Q87: 0.040935746 | R87: 30.720588
G88: PUN-L3-M4 | H88: 6990 | K88: Noida Factory | L88: 0.024209818 | M88: 27.333333
G89: BLR-L2-M2 | H89: 5724 | K89: Bengaluru Factory | L89: 0.044449425 | M89: 37.220884
A98: Q5 – Executive Summary | F98: Q6 – Executive Summary | K98: Q7 – Executive Summary | P98: Q8 – Executive Summary
A101: KEY FINDING | F101: KEY FINDING | K101: KEY FINDING | P101: KEY FINDING
A102: Nova Electronics has the poorest manufacturing quality from Q2 onward, with the highest weighted defect rate at 5.89% and 4,302 defective units. Within Nova Electronics, Grade B performs substantially worse, with an 8.05% defect rate versus 2.86% for Grade A. | F102: PUN-L3-M3, PUN-L3-M4, and BLR-L2-M2 stand out as the highest preventive-maintenance priorities. They have 97, 99, and 96 overdue maintenance records, respectively, together with very high accumulated downtime of 7,139, 6,990, and 5,724 minutes. | K102: The Night shift has the weakest overall operational performance, with the highest weighted defect rate (3.49%) and highest average machine downtime (35.18 min). Within the Night shift, Pune Factory combines a high 4.44% defect rate with the highest downtime (46.21 min). | P102: Noida Factory has the strongest operational profile for capacity expansion, recording the fewest safety incidents (7), lowest defect rate (2.13%), and lowest average machine downtime (23.25 min) among the four factories.
A108: CONCLUSION | F108: CONCLUSION | K108: CONCLUSION | P108: CONCLUSION
A109: The quality problem is concentrated rather than supplier-wide across all materials. Nova Electronics is the weakest supplier overall, with Grade B material representing the major quality concern. | F109: Preventive maintenance should be prioritized for machines showing both large overdue-maintenance backlogs and high downtime. PUN-L3-M3 and PUN-L3-M4 require the most immediate attention, followed by BLR-L2-M2. | K109: The Night-shift problem is not equally severe everywhere. It is particularly concentrated in Pune Factory, with machine-level analysis highlighting PUN-L3-M3 and PUN-L3-M4, which have defect rates of 5.36% and 5.27% and exceptionally high average downtime of 110.95 and 112.63 minutes. | P109: Noida Factory is the operationally safest choice for the next capacity expansion. Its combination of lower safety incidents, better quality performance, and lower machine downtime indicates less operational risk than Chennai, Pune, or Bengaluru.
A115: RECOMMENDATION | F115: RECOMMENDATION | K115: RECOMMENDATION | P115: RECOMMENDATION
A116: Prioritize a supplier quality review of Nova Electronics Grade B material, including incoming-material inspection and corrective-action discussions with the supplier. Increase monitoring of Grade B batches and consider alternative sourcing if defect performance does not improve. | F116: Schedule immediate preventive maintenance for PUN-L3-M3 and PUN-L3-M4, followed by BLR-L2-M2. Clear their overdue maintenance backlog first and monitor downtime after servicing to confirm that machine reliability improves. | K116: Prioritize a Night-shift operational review at Pune Factory, focusing first on PUN-L3-M3 and PUN-L3-M4. Investigate maintenance reliability, defect causes, staffing/shift practices, and operating conditions on these machines before applying broad changes across all Night-shift operations. | P116: Prioritize Noida Factory for the next capacity expansion, subject to final financial and capacity feasibility checks. Maintain safety and maintenance controls as utilization increases to prevent operational performance from deteriorating after expansion.
